Workbook

Sheet Application_Ledger
L1: Seller | O1: Buyer
A2: REF NO. | B2: LOA Number | C2: APPLICATION NO. | D2: APPROVAL NO. | E2: SELLER | F2: BUYER | G2: FROM DATE | H2: TO DATE | I2: APPLIED MWH | J2: APPROVED MWH | K2: Schedule MWH | L2: ISTS | M2: Application Fee | N2: RLDC Fee | O2: ISTS | P2: Application Fee | Q2: RLDC Fee
E3: 46113
A4: 154714 | B4: NVVN_Kreate_200MW | C4: SJVN010426WR2354 | D4: WR/2026/41024/C/R/0 | E4: NTPC Renewable Energy Limited_KPS3 | F4: M/s. GUJARAT ALKALIES ANDCHEMICALS LIMITED -13032 | G4: 46026 | H4: 46026 | I4: 205.95 | J4: 205.95 | K4: 205.95 | O4: 80568 | P4: 5000 | Q4: 1000
A5: 154718 | B5: NVVN_Kreate_200MW | C5: SJVN010426WR2355 | D5: WR/2026/41026/C/R/0 | E5: NTPC Renewable Energy Limited_KPS3 | F5: M/s. GUJARAT ALKALIES ANDCHEMICALS LIMITED -13032 | G5: 46026 | H5: 46026 | I5: 7.8 | J5: 7.8 | K5: 7.8 | O5: 3051 | P5: 5000 | Q5: 1000
A6: 158826 | B6: NVVN_Kreate_200MW | C6: SJVN250426WR2356 | D6: WR/2026/42379/C/R/0 | E6: NTPC Renewable Energy Limited_KPS3 | F6: M/s. GUJARAT ALKALIES ANDCHEMICALS LIMITED -13032 | G6: 25/04/2026 | H6: 25/04/2026 | I6: 215.375 | J6: 215.375 | K6: 215.375 | O6: 84255 | P6: 5000 | Q6: 1000
A7: 159167 | B7: NVVN_Kreate_200MW | C7: SJVN260426WR2357 | D7: WR/2026/42484/C/R/0 | E7: NTPC Renewable Energy Limited_KPS3 | F7: ELECTROTHERM (INDIA) LIMITED | G7: 26/04/2026 | H7: 26/04/2026 | I7: 135 | J7: 135 | K7: 135 | O7: 52812 | P7: 5000 | Q7: 1000
A8: 159169 | B8: NVVN_Kreate_200MW | C8: SJVN260426WR2358 | D8: WR/2026/42485/C/R/0 | E8: NTPC Renewable Energy Limited_KPS3 | F8: M/s. GUJARAT ALKALIES ANDCHEMICALS LIMITED -13032 | G8: 26/04/2026 | H8: 26/04/2026 | I8: 111.925 | J8: 111.925 | K8: 111.925 | O8: 43785 | P8: 5000 | Q8: 1000
A9: 159369 | B9: NVVN_Kreate_200MW | C9: SJVN270426WR2359 | D9: WR/2026/42553/C/R/0 | E9: NTPC Renewable Energy Limited_KPS3 | F9: ELECTROTHERM (INDIA) LIMITED | G9: 27/04/2026 | H9: 27/04/2026 | I9: 133 | J9: 133 | K9: 133 | O9: 51886 | P9: 5000 | Q9: 1000
A10: 159370 | B10: NVVN_Kreate_200MW | C10: SJVN270426WR2360 | D10: WR/2026/42554/C/R/0 | E10: NTPC Renewable Energy Limited_KPS3 | F10: M/s. GUJARAT ALKALIES ANDCHEMICALS LIMITED -13032 | G10: 27/04/2026 | H10: 27/04/2026 | I10: 410 | J10: 410 | K10: 410 | O10: 159949 | P10: 5000 | Q10: 1000
A11: 159372 | B11: NVVN_Kreate_200MW | C11: SJVN270426WR2361 | D11: WR/2026/42555/C/R/0 | E11: NTPC Renewable Energy Limited_KPS3 | F11: M/s. GUJARAT ALKALIES ANDCHEMICALS LIMITED -13032 | G11: 27/04/2026 | H11: 27/04/2026 | I11: 47.5 | J11: 47.5 | K11: 47.5 | O11: 18531 | P11: 5000 | Q11: 1000
A12: 159661 | B12: NVVN_Kreate_200MW | C12: SJVN280426WR2362 | D12: WR/2026/42647/C/R/0 | E12: NTPC Renewable Energy Limited_KPS3 | F12: M/s. GUJARAT ALKALIES ANDCHEMICALS LIMITED -13032 | G12: 28/04/2026 | H12: 28/04/2026 | I12: 475 | J12: 475 | K12: 475 | O12: 185307 | P12: 5000 | Q12: 1000
A13: 159670 | B13: NVVN_Kreate_200MW | C13: SJVN280426WR2363 | D13: WR/2026/42649/C/R/0 | E13: NTPC Renewable Energy Limited_KPS3 | F13: M/s. GUJARAT ALKALIES ANDCHEMICALS LIMITED -13032 | G13: 28/04/2026 | H13: 28/04/2026 | I13: 47.5 | J13: 47.5 | K13: 47.5 | O13: 18531 | P13: 5000 | Q13: 1000
A14: 159676 | B14: NVVN_Kreate_200MW | C14: SJVN280426WR2364 | D14: WR/2026/42650/C/R/0 | E14: NTPC Renewable Energy Limited_KPS3 | F14: ELECTROTHERM (INDIA) LIMITED | G14: 28/04/2026 | H14: 28/04/2026 | I14: 133 | J14: 133 | K14: 133 | O14: 51886 | P14: 5000 | Q14: 1000
A15: 159943 | B15: NVVN_Kreate_200MW | C15: SJVN290426WR2366 | D15: WR/2026/42743/C/R/0 | E15: NTPC Renewable Energy Limited_KPS3 | F15: M/s. GUJARAT ALKALIES ANDCHEMICALS LIMITED -13032 | G15: 29/04/2026 | H15: 29/04/2026 | I15: 450 | J15: 450 | K15: 450 | O15: 175554 | P15: 5000 | Q15: 1000
A16: 159944 | B16: NVVN_Kreate_200MW | C16: SJVN290426WR2369 | D16: WR/2026/42744/C/R/0 | E16: NTPC Renewable Energy Limited_KPS3 | F16: M/s. GUJARAT ALKALIES ANDCHEMICALS LIMITED -13032 | G16: 29/04/2026 | H16: 29/04/2026 | I16: 45 | J16: 45 | K16: 45 | O16: 17555 | P16: 5000 | Q16: 1000
A17: 159946 | B17: NVVN_Kreate_200MW | C17: SJVN290426WR2370 | D17: WR/2026/42746/C/R/0 | E17: NTPC Renewable Energy Limited_KPS3 | F17: ELECTROTHERM (INDIA) LIMITED | G17: 29/04/2026 | H17: 29/04/2026 | I17: 135 | J17: 135 | K17: 135 | O17: 52666 | P17: 5000 | Q17: 1000
... A20: 160246 | B20: NVVN_Kreate_200MW | C20: SJVN300426WR2373 | D20: WR/2026/42851/C/R/0 | E20: NTPC Renewable Energy Limited_KPS3 | F20: ELECTROTHERM (INDIA) LIMITED | G20: 30/04/2026 | H20: 30/04/2026 | I20: 135 | J20: 135 | K20: 135 | O20: 52666 | P20: 5000 | Q20: 1000
E21: 46143
A22: 160469 | B22: NVVN_Kreate_200MW | C22: SJVN010526WR2374 | D22: WR/2026/42914/C/R/0 | E22: NTPC Renewable Energy Limited_KPS3 | F22: M/s. GUJARAT ALKALIES ANDCHEMICALS LIMITED -13032 | G22: 46027 | H22: 46027 | I22: 248.925 | J22: 248.925 | K22: 248.925 | O22: 97111 | P22: 5000 | Q22: 1000
A23: 160475 | B23: NVVN_Kreate_200MW | C23: SJVN010526WR2376 | D23: WR/2026/42916/C/R/0 | E23: NTPC Renewable Energy Limited_KPS3 | F23: M/s. GUJARAT ALKALIES ANDCHEMICALS LIMITED -13032 | G23: 46027 | H23: 46027 | I23: 45 | J23: 45 | K23: 45 | O23: 17555 | P23: 5000 | Q23: 1000
A24: 160478 | B24: NVVN_Kreate_200MW | C24: SJVN010526WR2377 | D24: WR/2026/42918/C/R/0 | E24: NTPC Renewable Energy Limited_KPS3 | F24: ELECTROTHERM (INDIA) LIMITED | G24: 46027 | H24: 46027 | I24: 117 | J24: 117 | K24: 117 | O24: 45644 | P24: 5000 | Q24: 1000
A25: 160482 | B25: NVVN_Kreate_200MW | C25: SJVN010526ER2378 | D25: ER/2026/28089/C/R/0 | E25: NTPC Renewable Energy Limited_KPS3 | F25: NUVOCO VISTAS CORPORATION LIMITED (Mejia Cement Plant) | G25: 46027 | H25: 46027 | I25: 20.25 | J25: 20.25 | K25: 20.25 | O25: 8485 | P25: 5000 | Q25: 1000
A26: 160789 | B26: NVVN_Kreate_200MW | C26: SJVN020526WR2380 | D26: WR/2026/43030/C/R/0 | E26: NTPC Renewable Energy Limited_KPS3 | F26: M/s. GUJARAT ALKALIES ANDCHEMICALS LIMITED -13032 | G26: 46058 | H26: 46058 | I26: 315.625 | J26: 315.625 | K26: 315.625 | O26: 123132 | P26: 5000 | Q26: 1000
A27: 160938 | B27: NVVN_Kreate_200MW | C27: SJVN030526WR2381 | D27: WR/2026/43078/C/R/0 | E27: NTPC Renewable Energy Limited_KPS3 | F27: M/s. GUJARAT ALKALIES ANDCHEMICALS LIMITED -13032 | G27: 46086 | H27: 46086 | I27: 340.475 | J27: 340.475 | K27: 340.475 | O27: 132826 | P27: 5000 | Q27: 1000
A28: 160940 | B28: NVVN_Kreate_200MW | C28: SJVN030526WR2382 | D28: WR/2026/43079/C/R/0 | E28: NTPC Renewable Energy Limited_KPS3 | F28: ELECTROTHERM (INDIA) LIMITED | G28: 46086 | H28: 46086 | I28: 130 | J28: 130 | K28: 130 | O28: 50716 | P28: 5000 | Q28: 1000
A29: 161092 | B29: NVVN_Kreate_200MW | C29: SJVN040526WR2383 | D29: WR/2026/43131/C/R/0 | E29: NTPC Renewable Energy Limited_KPS3 | F29: M/s. GUJARAT ALKALIES ANDCHEMICALS LIMITED -13032 | G29: 46117 | H29: 46117 | I29: 98.6 | J29: 98.6 | K29: 98.6 | O29: 38466 | P29: 5000 | Q29: 1000
A30: 161093 | B30: NVVN_Kreate_200MW | C30: SJVN040526WR2384 | D30: WR/2026/43132/C/R/0 | E30: NTPC Renewable Energy Limited_KPS3 | F30: ELECTROTHERM (INDIA) LIMITED | G30: 46117 | H30: 46117 | I30: 123.5 | J30: 123.5 | K30: 123.5 | O30: 48180 | P30: 5000 | Q30: 1000
A31: 161199 | B31: NVVN_Kreate_200MW | C31: SJVN050526WR2385 | D31: WR/2026/43164/C/R/0 | E31: NTPC Renewable Energy Limited_KPS3 | F31: M/s. GUJARAT ALKALIES ANDCHEMICALS LIMITED -13032 | G31: 46147 | H31: 46147 | I31: 113.6 | J31: 113.6 | K31: 113.6 | O31: 44318 | P31: 5000 | Q31: 1000
A32: 161204 | B32: NVVN_Kreate_200MW | C32: SJVN050526WR2386 | D32: WR/2026/43165/C/R/0 | E32: NTPC Renewable Energy Limited_KPS3 | F32: ELECTROTHERM (INDIA) LIMITED | G32: 46147 | H32: 46147 | I32: 126 | J32: 126 | K32: 126 | O32: 49155 | P32: 5000 | Q32: 1000
A33: 161344 | B33: NVVN_Kreate_200MW | C33: SJVN060526WR2387 | D33: WR/2026/43202/C/R/0 | E33: NTPC Renewable Energy Limited_KPS3 | F33: M/s. GUJARAT ALKALIES ANDCHEMICALS LIMITED -13032 | G33: 46178 | H33: 46178 | I33: 225.725 | J33: 225.725 | K33: 225.725 | O33: 88060 | P33: 5000 | Q33: 1000
... A39: 161693 | B39: NVVN_Kreate_200MW | C39: SJVN080526WR2393 | D39: WR/2026/43302/C/R/0 | E39: NTPC Renewable Energy Limited_KPS3 | F39: ELECTROTHERM (INDIA) LIMITED | G39: 46239 | H39: 46239 | I39: 115.5 | J39: 115.5 | K39: 115.5 | O39: 45059 | P39: 5000 | Q39: 1000
A40: GNA | B40: NVVN_Kreate_200MW | C40: SJVN080526NR2394 | D40: GNARE/WR/2026/05/08/9765 | E40: NTPC Renewable Energy Limited_KPS3 | F40: Himachal Pradesh State Electricity Board Ltd. | G40: 46239 | H40: 46239 | I40: 240 | J40: 240 | K40: 240 | O40: 0 | P40: 0 | Q40: 0
A41: 161874 | B41: NVVN_Kreate_200MW | C41: SJVN090526WR2395 | D41: WR/2026/43365/C/R/0 | E41: NTPC Renewable Energy Limited_KPS3 | F41: M/s. GUJARAT ALKALIES ANDCHEMICALS LIMITED -13032 | G41: 46270 | H41: 46270 | I41: 194.65 | J41: 194.65 | K41: 194.65 | O41: 75937 | P41: 5000 | Q41: 1000
A42: 161878 | B42: NVVN_Kreate_200MW | C42: SJVN090526WR2396 | D42: WR/2026/43367/C/R/0 | E42: NTPC Renewable Energy Limited_KPS3 | F42: Shreeyam Power And Steel Industries Limited, Mithirohar | G42: 46270 | H42: 46270 | I42: 31.5 | J42: 31.5 | K42: 31.5 | O42: 12289 | P42: 5000 | Q42: 1000
A43: 161880 | B43: NVVN_Kreate_200MW | C43: SJVN090526WR2397 | D43: WR/2026/43380/C/R/0 | E43: NTPC Renewable Energy Limited_KPS3 | F43: M/s Gujarat Alkalies & Chemicals Limited | G43: 46270 | H43: 46270 | I43: 90.6 | J43: 90.6 | K43: 90.6 | O43: 35345 | P43: 5000 | Q43: 1000
A44: 161884 | B44: NVVN_Kreate_200MW | C44: SJVN090526WR2398 | D44: WR/2026/43370/C/R/0 | E44: NTPC Renewable Energy Limited_KPS3 | F44: ELECTROTHERM (INDIA) LIMITED | G44: 46270 | H44: 46270 | I44: 105 | J44: 105 | K44: 105 | O44: 40963 | P44: 5000 | Q44: 1000
A45: GNA | B45: NVVN_Kreate_200MW | C45: SJVN090526NR2399 | D45: GNARE/WR/2026/05/09/8855 | E45: NTPC Renewable Energy Limited_KPS3 | F45: Himachal Pradesh State Electricity Board Ltd. | G45: 46270 | H45: 46270 | I45: 344.455 | J45: 344.455 | K45: 344.455 | O45: 0 | P45: 0 | Q45: 0
A46: GNA | B46: NVVN_Kreate_200MW | C46: SJVN100526NR2400 | D46: GNARE/WR/2026/05/10/4068 | E46: NTPC Renewable Energy Limited_KPS3 | F46: Himachal Pradesh State Electricity Board Ltd. | G46: 46300 | H46: 46300 | I46: 400 | J46: 400 | K46: 400 | O46: 0 | P46: 0 | Q46: 0
A47: 162023 | B47: NVVN_Kreate_200MW | C47: SJVN100526WR2404 | D47: WR/2026/43415/C/R/0 | E47: NTPC Renewable Energy Limited_KPS3 | F47: M/s. GUJARAT ALKALIES ANDCHEMICALS LIMITED -13032 | G47: 46300 | H47: 46300 | I47: 254.0375 | J47: 254.0375 | K47: 254.0375 | O47: 99105 | P47: 5000 | Q47: 1000
A48: 162024 | B48: NVVN_Kreate_200MW | C48: SJVN100526WR2406 | D48: WR/2026/43416/C/R/0 | E48: NTPC Renewable Energy Limited_KPS3 | F48: M/s Gujarat Alkalies & Chemicals Limited | G48: 46300 | H48: 46300 | I48: 112.05 | J48: 112.05 | K48: 112.05 | O48: 43713 | P48: 5000 | Q48: 1000
A49: 162025 | B49: NVVN_Kreate_200MW | C49: SJVN100526WR2407 | D49: WR/2026/43417/C/R/0 | E49: NTPC Renewable Energy Limited_KPS3 | F49: ELECTROTHERM (INDIA) LIMITED | G49: 46300 | H49: 46300 | I49: 107.5 | J49: 107.5 | K49: 107.5 | O49: 41938 | P49: 5000 | Q49: 1000
A50: 162026 | B50: NVVN_Kreate_200MW | C50: SJVN100526WR2408 | D50: WR/2026/43418/C/R/0 | E50: NTPC Renewable Energy Limited_KPS3 | F50: Shreeyam Power And Steel Industries Limited, Mithirohar | G50: 46300 | H50: 46300 | I50: 43 | J50: 43 | K50: 43 | O50: 16775 | P50: 5000 | Q50: 1000
A51: GNA | B51: NVVN_Kreate_200MW | C51: SJVN110526NR2401 | D51: GNARE/WR/2026/05/11/4345 | E51: NTPC Renewable Energy Limited_KPS3 | F51: Himachal Pradesh State Electricity Board Ltd. | G51: 46331 | H51: 46331 | I51: 240 | J51: 240 | K51: 240 | O51: 0 | P51: 0 | Q51: 0
A52: 162133 | B52: NVVN_Kreate_200MW | C52: SJVN110526WR2409 | D52: WR/2026/43446/C/R/0 | E52: NTPC Renewable Energy Limited_KPS3 | F52: GACL NALCO Alkalies & Chemicals Pvt Ltd Cons.No.63869 | G52: 46331 | H52: 46331 | I52: 185.35 | J52: 185.35 | K52: 185.35 | O52: 72309 | P52: 5000 | Q52: 1000
A53: 162137 | B53: NVVN_Kreate_200MW | C53: SJVN110526WR2410 | D53: WR/2026/43447/C/R/0 | E53: NTPC Renewable Energy Limited_KPS3 | F53: Shreeyam Power And Steel Industries Limited, Mithirohar | G53: 46331 | H53: 46331 | I53: 43 | J53: 43 | K53: 43 | O53: 16775 | P53: 5000 | Q53: 1000
A54: 162140 | B54: NVVN_Kreate_200MW | C54: SJVN110526WR2411 | D54: WR/2026/43448/C/R/0 | E54: NTPC Renewable Energy Limited_KPS3 | F54: M/s Gujarat Alkalies & Chemicals Limited | G54: 46331 | H54: 46331 | I54: 91.5 | J54: 91.5 | K54: 91.5 | O54: 35696 | P54: 5000 | Q54: 1000
A55: GNA | B55: NVVN_Kreate_200MW | C55: SJVN120526NR2402 | D55: GNARE/WR/2026/05/12/5034 | E55: NTPC Renewable Energy Limited_KPS3 | F55: Himachal Pradesh State Electricity Board Ltd. | G55: 46361 | H55: 46361 | I55: 240 | J55: 240 | K55: 240 | O55: 0 | P55: 0 | Q55: 0
A56: 162261 | B56: NVVN_Kreate_200MW | C56: SJVN120526WR2412 | D56: WR/2026/43492/C/R/0 | E56: NTPC Renewable Energy Limited_KPS3 | F56: Shreeyam Power And Steel Industries Limited, Mithirohar | G56: 46361 | H56: 46361 | I56: 42 | J56: 42 | K56: 42 | O56: 16385 | P56: 5000 | Q56: 1000
A57: 162262 | B57: NVVN_Kreate_200MW | C57: SJVN120526WR2413 | D57: WR/2026/43493/C/R/0 | E57: NTPC Renewable Energy Limited_KPS3 | F57: ELECTROTHERM (INDIA) LIMITED | G57: 46361 | H57: 46361 | I57: 126 | J57: 126 | K57: 126 | O57: 49155 | P57: 5000 | Q57: 1000
A58: 162265 | B58: NVVN_Kreate_200MW | C58: SJVN120526WR2414 | D58: WR/2026/43494/C/R/0 | E58: NTPC Renewable Energy Limited_KPS3 | F58: GACL NALCO Alkalies & Chemicals Pvt Ltd Cons.No.63869 | G58: 46361 | H58: 46361 | I58: 195.9 | J58: 195.9 | K58: 195.9 | O58: 76425 | P58: 5000 | Q58: 1000
A59: 162269 | B59: NVVN_Kreate_200MW | C59: SJVN120526WR2415 | D59: WR/2026/43497/C/R/0 | E59: NTPC Renewable Energy Limited_KPS3 | F59: M/s Gujarat Alkalies & Chemicals Limited | G59: 46361 | H59: 46361 | I59: 88.75 | J59: 88.75 | K59: 88.75 | O59: 34623 | P59: 5000 | Q59: 1000
A60: 162427 | B60: NVVN_Kreate_200MW | C60: SJVN130526WR2416 | D60: WR/2026/43541/C/R/0 | E60: NTPC Renewable Energy Limited_KPS3 | F60: GACL NALCO Alkalies & Chemicals Pvt Ltd Cons.No.63869 | G60: 13/05/2026 | H60: 13/05/2026 | I60: 198.2 | J60: 198.2 | K60: 165.05 | O60: 77322 | P60: 5000 | Q60: 1000
A61: 162440 | B61: NVVN_Kreate_200MW | C61: SJVN130526WR2417 | D61: WR/2026/43542/C/R/0 | E61: NTPC Renewable Energy Limited_KPS3 | F61: Shreeyam Power And Steel Industries Limited, Mithirohar | G61: 13/05/2026 | H61: 13/05/2026 | I61: 42 | J61: 42 | K61: 35 | O61: 16385 | P61: 5000 | Q61: 1000
A62: 162443 | B62: NVVN_Kreate_200MW | C62: SJVN130526WR2418 | D62: WR/2026/43543/C/R/0 | E62: NTPC Renewable Energy Limited_KPS3 | F62: ELECTROTHERM (INDIA) LIMITED | G62: 13/05/2026 | H62: 13/05/2026 | I62: 141.75 | J62: 141.75 | K62: 118.125 | O62: 55300 | P62: 5000 | Q62: 1000
A63: 162446 | B63: NVVN_Kreate_200MW | C63: SJVN130526WR2419 | D63: WR/2026/43545/C/R/0 | E63: NTPC Renewable Energy Limited_KPS3 | F63: M/s Gujarat Alkalies & Chemicals Limited | G63: 13/05/2026 | H63: 13/05/2026 | I63: 112.75 | J63: 112.75 | K63: 74.25 | O63: 43986 | P63: 5000 | Q63: 1000
A64: 162621 | B64: NVVN_Kreate_200MW | C64: SJVN140526WR2420 | D64: WR/2026/43594/C/R/0 | E64: NTPC Renewable Energy Limited_KPS3 | F64: GACL NALCO Alkalies & Chemicals Pvt Ltd Cons.No.63869 | G64: 14/05/2026 | H64: 14/05/2026 | I64: 165.4 | J64: 165.4 | K64: 83.15 | O64: 64526 | P64: 5000 | Q64: 1000
A65: 162622 | B65: NVVN_Kreate_200MW | C65: SJVN140526WR2421 | D65: WR/2026/43597/C/R/0 | E65: NTPC Renewable Energy Limited_KPS3 | F65: Shreeyam Power And Steel Industries Limited, Mithirohar | G65: 14/05/2026 | H65: 14/05/2026 | I65: 41 | J65: 41 | K65: 23 | O65: 15995 | P65: 5000 | Q65: 1000
A66: 162623 | B66: NVVN_Kreate_200MW | C66: SJVN140526WR2422 | D66: WR/2026/43599/C/R/0 | E66: NTPC Renewable Energy Limited_KPS3 | F66: ELECTROTHERM (INDIA) LIMITED | G66: 14/05/2026 | H66: 14/05/2026 | I66: 102.5 | J66: 102.5 | K66: 57.5 | O66: 39987 | P66: 5000 | Q66: 1000
A67: 162625 | B67: NVVN_Kreate_200MW | C67: SJVN140526WR2423 | D67: WR/2026/43601/C/R/0 | E67: NTPC Renewable Energy Limited_KPS3 | F67: M/s Gujarat Alkalies & Chemicals Limited | G67: 14/05/2026 | H67: 14/05/2026 | I67: 107.5 | J67: 107.5 | K67: 58.25 | O67: 41938 | P67: 5000 | Q67: 1000
A68: 162838 | B68: NVVN_Kreate_200MW | C68: SJVN150526WR2424 | D68: WR/2026/43659/C/R/0 | E68: NTPC Renewable Energy Limited_KPS3 | F68: GACL NALCO Alkalies & Chemicals Pvt Ltd Cons.No.63869 | G68: 15/05/2026 | H68: 15/05/2026 | I68: 183.275 | J68: 183.275 | K68: 183.275 | O68: 71499 | P68: 5000 | Q68: 1000
A69: 162843 | B69: NVVN_Kreate_200MW | C69: SJVN150526NR2425 | D69: NR/2026/43177/C/R/0 | E69: NTPC Renewable Energy Limited_KPS3 | F69: Fortis Hospotel Limited | G69: 15/05/2026 | H69: 15/05/2026 | I69: 18.2 | J69: 18.2 | K69: 18.2 | O69: 9262 | P69: 5000 | Q69: 1000
A70: 162846 | B70: NVVN_Kreate_200MW | C70: SJVN150526WR2426 | D70: WR/2026/43661/C/R/0 | E70: NTPC Renewable Energy Limited_KPS3 | F70: Shreeyam Power And Steel Industries Limited, Mithirohar | G70: 15/05/2026 | H70: 15/05/2026 | I70: 39 | J70: 39 | K70: 39 | O70: 15215 | P70: 5000 | Q70: 1000
A71: 162849 | B71: NVVN_Kreate_200MW | C71: SJVN150526WR2427 | D71: WR/2026/43664/C/R/0 | E71: NTPC Renewable Energy Limited_KPS3 | F71: ELECTROTHERM (INDIA) LIMITED | G71: 15/05/2026 | H71: 15/05/2026 | I71: 39 | J71: 39 | K71: 39 | O71: 15215 | P71: 5000 | Q71: 1000
... A96: 163642 | B96: NVVN_Kreate_200MW | C96: SJVN200526WR2455 | D96: WR/2026/43894/C/R/0 | E96: NTPC Renewable Energy Limited_KPS3 | F96: M/s Gujarat Alkalies & Chemicals Limited | G96: 20/05/2026 | H96: 20/05/2026 | I96: 79.5 | J96: 79.5 | K96: 79.5 | O96: 31015 | P96: 5000 | Q96: 1000
B97: NVVN_Kreate_200MW | C97: SJVN200526NR2446 | D97: NR/2026/43317/A/R/0 | E97: NTPC Renewable Energy Limited_KPS3 | F97: Fortis Hospotel Limited | G97: 20/05/2026 | H97: 21/05/2026 | I97: 29.6 | J97: 29.6 | K97: 29.6 | O97: 15064 | P97: 5000 | Q97: 2000
A98: 163825 | B98: NVVN_Kreate_200MW | C98: SJVN210526WR2457 | D98: WR/2026/43935/C/R/0 | E98: NTPC Renewable Energy Limited_KPS3 | F98: M/s. GUJARAT ALKALIES ANDCHEMICALS LIMITED -13032 | G98: 21/05/2026 | H98: 21/05/2026 | I98: 284.5 | J98: 284.5 | K98: 284.5 | O98: 110989 | P98: 5000 | Q98: 1000
A99: 163827 | B99: NVVN_Kreate_200MW | C99: SJVN210526WR2458 | D99: WR/2026/43936/C/R/0 | E99: NTPC Renewable Energy Limited_KPS3 | F99: Shreeyam Power And Steel Industries Limited, Mithirohar | G99: 21/05/2026 | H99: 21/05/2026 | I99: 36 | J99: 36 | K99: 36 | O99: 14044 | P99: 5000 | Q99: 1000
A100: 163833 | B100: NVVN_Kreate_200MW | C100: SJVN210526WR2459 | D100: WR/2026/43937/C/R/0 | E100: NTPC Renewable Energy Limited_KPS3 | F100: ELECTROTHERM (INDIA) LIMITED | G100: 21/05/2026 | H100: 21/05/2026 | I100: 133 | J100: 133 | K100: 133 | O100: 51886 | P100: 5000 | Q100: 1000
A101: 163835 | B101: NVVN_Kreate_200MW | C101: SJVN210526WR2460 | D101: WR/2026/43938/C/R/0 | E101: NTPC Renewable Energy Limited_KPS3 | F101: M/s Gujarat Alkalies & Chemicals Limited | G101: 21/05/2026 | H101: 21/05/2026 | I101: 88 | J101: 88 | K101: 88 | O101: 34331 | P101: 5000 | Q101: 1000
A102: 163836 | B102: NVVN_Kreate_200MW | C102: SJVN210526WR2461 | D102: WR/2026/43939/C/R/0 | E102: NTPC Renewable Energy Limited_KPS3 | F102: GACL NALCO Alkalies & Chemicals Pvt Ltd Cons.No.63869 | G102: 21/05/2026 | H102: 21/05/2026 | I102: 175.775 | J102: 175.775 | K102: 175.775 | O102: 68573 | P102: 5000 | Q102: 1000
A103: 164178 | B103: NVVN_Kreate_200MW | C103: SJVN220526WR2462 | D103: WR/2026/44010/C/R/0 | E103: NTPC Renewable Energy Limited_KPS3 | F103: GACL NALCO Alkalies & Chemicals Pvt Ltd Cons.No.63869 | G103: 22/05/2026 | H103: 22/05/2026 | I103: 177.05 | J103: 177.05 | K103: 177.05 | O103: 69071 | P103: 5000 | Q103: 1000
A104: 164186 | B104: NVVN_Kreate_200MW | C104: SJVN220526NR2463 | D104: NR/2026/43541/C/R/0 | E104: NTPC Renewable Energy Limited_KPS3 | F104: Fortis Hospotel Limited | G104: 22/05/2026 | H104: 22/05/2026 | I104: 14.8 | J104: 14.8 | K104: 14.8 | O104: 7532 | P104: 5000 | Q104: 1000
A105: 164204 | B105: NVVN_Kreate_200MW | C105: SJVN220526WR2464 | D105: WR/2026/44013/C/R/0 | E105: NTPC Renewable Energy Limited_KPS3 | F105: M/s. GUJARAT ALKALIES ANDCHEMICALS LIMITED -13032 | G105: 22/05/2026 | H105: 22/05/2026 | I105: 332.5 | J105: 332.5 | K105: 332.5 | O105: 129715 | P105: 5000 | Q105: 1000
A106: 164210 | B106: NVVN_Kreate_200MW | C106: SJVN220526WR2465 | D106: WR/2026/44015/C/R/0 | E106: NTPC Renewable Energy Limited_KPS3 | F106: Shreeyam Power And Steel Industries Limited, Mithirohar | G106: 22/05/2026 | H106: 22/05/2026 | I106: 36 | J106: 36 | K106: 36 | O106: 14044 | P106: 5000 | Q106: 1000
A107: 164216 | B107: NVVN_Kreate_200MW | C107: SJVN220526WR2466 | D107: WR/2026/44017/C/R/0 | E107: NTPC Renewable Energy Limited_KPS3 | F107: ELECTROTHERM (INDIA) LIMITED | G107: 22/05/2026 | H107: 22/05/2026 | I107: 133 | J107: 133 | K107: 133 | O107: 51886 | P107: 5000 | Q107: 1000
A108: 164221 | B108: NVVN_Kreate_200MW | C108: SJVN220526WR2467 | D108: WR/2026/44018/C/R/0 | E108: NTPC Renewable Energy Limited_KPS3 | F108: M/s Gujarat Alkalies & Chemicals Limited | G108: 22/05/2026 | H108: 22/05/2026 | I108: 94.25 | J108: 94.25 | K108: 94.25 | O108: 36769 | P108: 5000 | Q108: 1000
A109: 164448 | B109: NVVN_Kreate_200MW | C109: SJVN230526WR2469 | D109: WR/2026/44064/C/R/0 | E109: NTPC Renewable Energy Limited_KPS3 | F109: GACL NALCO Alkalies & Chemicals Pvt Ltd Cons.No.63869 | G109: 23/05/2026 | H109: 23/05/2026 | I109: 177.2 | J109: 177.2 | K109: 177.2 | O109: 69129 | P109: 5000 | Q109: 1000
... A119: 164685 | B119: NVVN_Kreate_200MW | C119: SJVN240526WR2479 | D119: WR/2026/44140/C/R/0 | E119: NTPC Renewable Energy Limited_KPS3 | F119: M/s Gujarat Alkalies & Chemicals Limited | G119: 24/05/2026 | H119: 24/05/2026 | I119: 105 | J119: 105 | K119: 105 | O119: 40963 | P119: 5000 | Q119: 1000
B120: NVVN_Kreate_200MW | C120: SJVN240526NR2468 | D120: NR/2026/43552/A/R/0 | E120: NTPC Renewable Energy Limited_KPS3 | F120: Fortis Hospotel Limited | G120: 24/05/2026 | H120: 31/05/2026 | I120: 118.4 | J120: 118.4 | K120: 118.4 | O120: 60256 | P120: 5000 | Q120: 8000
A121: 164866 | B121: NVVN_Kreate_200MW | C121: SJVN250526WR2480 | D121: WR/2026/44174/C/R/0 | E121: NTPC Renewable Energy Limited_KPS3 | F121: GACL NALCO Alkalies & Chemicals Pvt Ltd Cons.No.63869 | G121: 25/05/2026 | H121: 25/05/2026 | I121: 248.1 | J121: 248.1 | K121: 248.1 | O121: 96789 | P121: 5000 | Q121: 1000
A122: 164873 | B122: NVVN_Kreate_200MW | C122: SJVN250526WR2481 | D122: WR/2026/44175/C/R/0 | E122: NTPC Renewable Energy Limited_KPS3 | F122: M/s. GUJARAT ALKALIES ANDCHEMICALS LIMITED -13032 | G122: 25/05/2026 | H122: 25/05/2026 | I122: 332.5 | J122: 332.5 | K122: 332.5 | O122: 129715 | P122: 5000 | Q122: 1000
A123: 164877 | B123: NVVN_Kreate_200MW | C123: SJVN250526WR2482 | D123: WR/2026/44176/C/R/0 | E123: NTPC Renewable Energy Limited_KPS3 | F123: Shreeyam Power And Steel Industries Limited, Mithirohar | G123: 25/05/2026 | H123: 25/05/2026 | I123: 36 | J123: 36 | K123: 36 | O123: 14044 | P123: 5000 | Q123: 1000
A124: 164881 | B124: NVVN_Kreate_200MW | C124: SJVN250526WR2483 | D124: WR/2026/44177/C/R/0 | E124: NTPC Renewable Energy Limited_KPS3 | F124: ELECTROTHERM (INDIA) LIMITED | G124: 25/05/2026 | H124: 25/05/2026 | I124: 128.25 | J124: 128.25 | K124: 128.25 | O124: 50033 | P124: 5000 | Q124: 1000
A125: 164885 | B125: NVVN_Kreate_200MW | C125: SJVN250526WR2484 | D125: WR/2026/44179/C/R/0 | E125: NTPC Renewable Energy Limited_KPS3 | F125: M/s Gujarat Alkalies & Chemicals Limited | G125: 25/05/2026 | H125: 25/05/2026 | I125: 89.75 | J125: 89.75 | K125: 89.75 | O125: 35013 | P125: 5000 | Q125: 1000
A126: 165097 | B126: NVVN_Kreate_200MW | C126: SJVN260526WR2491 | D126: WR/2026/44220/C/R/0 | E126: NTPC Renewable Energy Limited_KPS3 | F126: M/s Gujarat Alkalies & Chemicals Limited | G126: 26/05/2026 | H126: 26/05/2026 | I126: 72.25 | J126: 72.25 | K126: 72.25 | O126: 28186 | P126: 5000 | Q126: 1000
A127: 165113 | B127: NVVN_Kreate_200MW | C127: SJVN260526WR2492 | D127: WR/2026/44227/C/R/0 | E127: NTPC Renewable Energy Limited_KPS3 | F127: GACL NALCO Alkalies & Chemicals Pvt Ltd Cons.No.63869 | G127: 26/05/2026 | H127: 26/05/2026 | I127: 247.275 | J127: 247.275 | K127: 247.275 | O127: 96467 | P127: 5000 | Q127: 1000
A128: 165117 | B128: NVVN_Kreate_200MW | C128: SJVN260526WR2493 | D128: WR/2026/44228/C/R/0 | E128: NTPC Renewable Energy Limited_KPS3 | F128: M/s. GUJARAT ALKALIES ANDCHEMICALS LIMITED -13032 | G128: 26/05/2026 | H128: 26/05/2026 | I128: 162.5 | J128: 162.5 | K128: 162.5 | O128: 63394 | P128: 5000 | Q128: 1000
A129: 165119 | B129: NVVN_Kreate_200MW | C129: SJVN260526WR2494 | D129: WR/2026/44229/C/R/0 | E129: NTPC Renewable Energy Limited_KPS3 | F129: Shreeyam Power And Steel Industries Limited, Mithirohar | G129: 26/05/2026 | H129: 26/05/2026 | I129: 36 | J129: 36 | K129: 36 | O129: 14044 | P129: 5000 | Q129: 1000
A130: 165122 | B130: NVVN_Kreate_200MW | C130: SJVN260526WR2495 | D130: WR/2026/44230/C/R/0 | E130: NTPC Renewable Energy Limited_KPS3 | F130: ELECTROTHERM (INDIA) LIMITED | G130: 26/05/2026 | H130: 26/05/2026 | I130: 128.25 | J130: 128.25 | K130: 128.25 | O130: 50033 | P130: 5000 | Q130: 1000
A131: 165386 | B131: NVVN_Kreate_200MW | C131: SJVN270526WR2496 | D131: WR/2026/44288/C/R/0 | E131: NTPC Renewable Energy Limited_KPS3 | F131: GACL NALCO Alkalies & Chemicals Pvt Ltd Cons.No.63869 | G131: 27/05/2026 | H131: 27/05/2026 | I131: 234.925 | J131: 234.925 | K131: 234.925 | O131: 84385 | P131: 5000 | Q131: 1000
A132: 165388 | B132: NVVN_Kreate_200MW | C132: SJVN270526WR2497 | D132: WR/2026/44290/C/R/0 | E132: NTPC Renewable Energy Limited_KPS3 | F132: M/s. GUJARAT ALKALIES ANDCHEMICALS LIMITED -13032 | G132: 27/05/2026 | H132: 27/05/2026 | I132: 162.5 | J132: 162.5 | K132: 162.5 | O132: 58370 | P132: 5000 | Q132: 1000
... A154: 166317 | B154: NVVN_Kreate_200MW | C154: SJVN310526WR2522 | D154: WR/2026/44555/C/R/0 | E154: NTPC Renewable Energy Limited_KPS3 | F154: M/s. GUJARAT ALKALIES AND CHEMICALS LIMITED | G154: 31/05/2026 | H154: 31/05/2026 | I154: 52.5 | J154: 52.5 | K154: 52.5 | O154: 18858 | P154: 5000 | Q154: 1000
E155: 46174
A156: 166584 | B156: NVVN_Kreate_200MW | C156: SJVN010626WR2523 | D156: WR/2026/44611/C/R/0 | E156: NTPC Renewable Energy Limited_KPS3 | F156: GACL NALCO Alkalies & Chemicals Pvt Ltd Cons.No.63869 | G156: 46028 | H156: 46028 | I156: 311.975 | J156: 311.975 | K156: 311.975 | O156: 112061 | P156: 5000 | Q156: 1000
A157: 166588 | B157: NVVN_Kreate_200MW | C157: SJVN010626WR2524 | D157: WR/2026/44617/C/R/0 | E157: NTPC Renewable Energy Limited_KPS3 | F157: M/s. GUJARAT ALKALIES ANDCHEMICALS LIMITED -13032 | G157: 46028 | H157: 46028 | I157: 269.8 | J157: 269.8 | K157: 269.8 | O157: 96912 | P157: 5000 | Q157: 1000
A158: 166591 | B158: NVVN_Kreate_200MW | C158: SJVN010626WR2525 | D158: WR/2026/44620/C/R/0 | E158: NTPC Renewable Energy Limited_KPS3 | F158: Shreeyam Power And Steel Industries Limited, Mithirohar | G158: 46028 | H158: 46028 | I158: 35 | J158: 35 | K158: 35 | O158: 12572 | P158: 5000 | Q158: 1000
A159: 166595 | B159: NVVN_Kreate_200MW | C159: SJVN010626WR2526 | D159: WR/2026/44622/C/R/0 | E159: NTPC Renewable Energy Limited_KPS3 | F159: ELECTROTHERM (INDIA) LIMITED | G159: 46028 | H159: 46028 | I159: 117 | J159: 117 | K159: 117 | O159: 42026 | P159: 5000 | Q159: 1000
A160: 166598 | B160: NVVN_Kreate_200MW | C160: SJVN010626WR2527 | D160: WR/2026/44623/C/R/0 | E160: NTPC Renewable Energy Limited_KPS3 | F160: M/s. GUJARAT ALKALIES AND CHEMICALS LIMITED | G160: 46028 | H160: 46028 | I160: 86.75 | J160: 86.75 | K160: 86.75 | O160: 31161 | P160: 5000 | Q160: 1000
A161: 166843 | B161: NVVN_Kreate_200MW | C161: SJVN020626WR2528 | D161: WR/2026/44671/C/R/0 | E161: NTPC Renewable Energy Limited_KPS3 | F161: GACL NALCO Alkalies & Chemicals Pvt Ltd Cons.No.63869 | G161: 46059 | H161: 46059 | I161: 333.225 | J161: 333.225 | K161: 333.225 | O161: 119694 | P161: 5000 | Q161: 1000
...

Sheet Daily Schedule
C1: NTPC VIDYUT VYAPAR NIGAM LIMITED & KREAT Energy India Pvt Ltd 200MW
B2: Date | C2: Availability (MWh) | D2: Kreate Requested (MWh) | E2: Actual Scheduled (MWh) | F2: Default from Kreate (MWh) | G2: Default from NVVN (MWh) | H2: Remark
B3: 46026 | C3: 2027.81 | D3: =Application_Ledger!J4+Application_Ledger!J5 -> 213.75 | E3: =Application_Ledger!K4+Application_Ledger!K5 -> 213.75 | F3: 0 | G3: =D3-E3 -> 0
B4: 25/04/2026 | C4: 2223.5 | D4: =Application_Ledger!J6 -> 215.375 | E4: =Application_Ledger!K6 -> 215.375 | F4: 0 | G4: =D4-E4 -> 0
B5: 26/04/2026 | C5: 2143.25 | D5: =Application_Ledger!J7+Application_Ledger!J8 -> 246.925 | E5: =Application_Ledger!K7+Application_Ledger!K8 -> 246.925 | F5: 0 | G5: =D5-E5 -> 0
B6: 27/04/2026 | C6: 2143.25 | D6: =Application_Ledger!J9+Application_Ledger!J10+Application_Ledger!J11 -> 590.5 | E6: =Application_Ledger!K9+Application_Ledger!K10+Application_Ledger!K11 -> 590.5 | F6: 0 | G6: =D6-E6 -> 0
B7: 28/04/2026 | C7: 2143.25 | D7: =Application_Ledger!J12+Application_Ledger!J13+Application_Ledger!J14 -> 655.5 | E7: =Application_Ledger!K12+Application_Ledger!K13+Application_Ledger!K14 -> 655.5 | F7: 0 | G7: =D7-E7 -> 0
B8: 29/04/2026 | C8: 2143.25 | D8: =Application_Ledger!J15+Application_Ledger!J16+Application_Ledger!J17 -> 630 | E8: =Application_Ledger!K15+Application_Ledger!K16+Application_Ledger!K17 -> 630 | F8: 0 | G8: =D8-E8 -> 0
B9: 30/04/2026 | C9: 2143.25 | D9: =Application_Ledger!J18+Application_Ledger!J19+Application_Ledger!J20 -> 539 | E9: =Application_Ledger!K18+Application_Ledger!K19+Application_Ledger!K20 -> 539 | F9: 0 | G9: =D9-E9 -> 0
B10: Monthly Total | C10: =SUM(C3:C9) -> 14967.56 | D10: =SUM(D3:D9) -> 3091.05 | E10: =SUM(E3:E9) -> 3091.05 | F10: =SUM(F3:F9) -> 0 | G10: =SUM(G3:G9) -> 0
B11: 46027 | C11: 2143.25 | D11: =Application_Ledger!J22+Application_Ledger!J23+Application_Ledger!J24+Application_Ledger!J25 -> 431.175 | E11: =Application_Ledger!K22+Application_Ledger!K23+Application_Ledger!K24+Application_Ledger!K25 -> 431.175 | F11: 0 | G11: =D11-E11 -> 0
B12: 46058 | C12: 2143.25 | D12: =Application_Ledger!J26 -> 315.625 | E12: =Application_Ledger!K26 -> 315.625 | F12: 0 | G12: =D12-E12 -> 0
B13: 46086 | C13: 2143.25 | D13: =Application_Ledger!J27+Application_Ledger!J28 -> 470.475 | E13: =Application_Ledger!K27+Application_Ledger!K28 -> 470.475 | F13: 0 | G13: =D13-E13 -> 0
B14: 46117 | C14: 2143.25 | D14: =Application_Ledger!J29+Application_Ledger!J30 -> 222.1 | E14: =Application_Ledger!K29+Application_Ledger!K30 -> 222.1 | F14: 0 | G14: =D14-E14 -> 0
B15: 46147 | C15: 2143.25 | D15: =Application_Ledger!J31+Application_Ledger!J32 -> 239.6 | E15: =Application_Ledger!K31+Application_Ledger!K32 -> 239.6 | F15: 0 | G15: =D15-E15 -> 0
B16: 46178 | C16: 2143.25 | D16: =Application_Ledger!J33+Application_Ledger!J34 -> 330.725 | E16: =Application_Ledger!K33+Application_Ledger!K34 -> 330.725 | F16: 0 | G16: =D16-E16 -> 0
B17: 46208 | C17: 2143.25 | D17: =Application_Ledger!J35+Application_Ledger!J36 -> 341.4 | E17: =Application_Ledger!K35+Application_Ledger!K36 -> 341.4 | F17: 0 | G17: =D17-E17 -> 0
B18: 46239 | C18: 2143.25 | D18: =Application_Ledger!J37+Application_Ledger!J38+Application_Ledger!J39+Application_Ledger!J40 -> 749.025 | E18: =Application_Ledger!K37+Application_Ledger!K38+Application_Ledger!K39+Application_Ledger!K40 -> 749.025 | F18: 0 | G18: =D18-E18 -> 0
B19: 46270 | C19: 2143.25 | D19: =sum(Application_Ledger!J41:J45) -> 766.205 | E19: =sum(Application_Ledger!K41:K45) -> 766.205 | F19: 0 | G19: =D19-E19 -> 0
B20: 46300 | C20: 2143.25 | D20: =Application_Ledger!J46+Application_Ledger!J47+Application_Ledger!J48+Application_Ledger!J49+Application_Ledger!J50 -> 916.5875 | E20: =Application_Ledger!K46+Application_Ledger!K47+Application_Ledger!K48+Application_Ledger!K49+Application_Ledger!K50 -> 916.5875 | F20: 0 | G20: =D20-E20 -> 0
B21: 46331 | C21: 2143.25 | D21: =Application_Ledger!J51+Application_Ledger!J52+Application_Ledger!J53+Application_Ledger!J54 -> 559.85 | E21: =Application_Ledger!K51+Application_Ledger!K52+Application_Ledger!K53+Application_Ledger!K54 -> 559.85 | F21: 0 | G21: =D21-E21 -> 0
B22: 46361 | C22: 2143.25 | D22: =Application_Ledger!J55+Application_Ledger!J56+Application_Ledger!J57+Application_Ledger!J58+Application_Ledger!J59 -> 692.65 | E22: =Application_Ledger!K55+Application_Ledger!K56+Application_Ledger!K57+Application_Ledger!K58+Application_Ledger!K59 -> 692.65 | F22: 0 | G22: =D22-E22 -> 0
B23: 13/05/2026 | C23: 2143.25 | D23: =sum(Application_Ledger!J60:J63) -> 494.7 | E23: =sum(Application_Ledger!K60:K63) -> 392.425 | F23: 0 | G23: =D23-E23 -> 102.275
B24: 14/05/2026 | C24: 2143.25 | D24: =sum(Application_Ledger!J64:J67) -> 416.4 | E24: =sum(Application_Ledger!K64:K67) -> 221.9 | F24: 0 | G24: =D24-E24 -> 194.5
B25: 15/05/2026 | C25: 2143.25 | D25: =sum(Application_Ledger!J68:J72) -> 376.975 | E25: =sum(Application_Ledger!K68:K72) -> 376.975 | F25: 0 | G25: =D25-E25 -> 0
B26: 16/05/2026 | C26: 2143.25 | D26: =Application_Ledger!J73+Application_Ledger!J74+Application_Ledger!J75+Application_Ledger!J76+Application_Ledger!J77 -> 314.85 | E26: =Application_Ledger!K73+Application_Ledger!K74+Application_Ledger!K75+Application_Ledger!K76+Application_Ledger!K77 -> 314.85 | F26: 0 | G26: =D26-E26 -> 0
B27: 17/05/2026 | C27: 2143.25 | D27: =Application_Ledger!J78+Application_Ledger!J79+Application_Ledger!J80+Application_Ledger!J81+Application_Ledger!J82 -> 409.6 | E27: =Application_Ledger!K78+Application_Ledger!K79+Application_Ledger!K80+Application_Ledger!K81+Application_Ledger!K82 -> 393.25 | F27: 0 | G27: =D27-E27 -> 16.35
B28: 18/05/2026 | C28: 2143.25 | D28: =Application_Ledger!K83+Application_Ledger!K84+Application_Ledger!K85+Application_Ledger!K86+Application_Ledger!K87 -> 435.975 | E28: =Application_Ledger!K83+Application_Ledger!K84+Application_Ledger!K85+Application_Ledger!K86+Application_Ledger!K87 -> 435.975 | F28: 0 | G28: =D28-E28 -> 0
B29: 19/05/2026 | C29: 2143.25 | D29: =Application_Ledger!J88+Application_Ledger!J89+Application_Ledger!J90+Application_Ledger!J91+Application_Ledger!J92 -> 374 | E29: =Application_Ledger!K88+Application_Ledger!K89+Application_Ledger!K90+Application_Ledger!K91+Application_Ledger!K92 -> 374 | F29: 0 | G29: =D29-E29 -> 0
B30: 20/05/2026 | C30: 2143.25 | D30: =Application_Ledger!J93+Application_Ledger!J94+Application_Ledger!J95+Application_Ledger!J96+14.8 -> 431 | E30: =Application_Ledger!K93+Application_Ledger!K94+Application_Ledger!K95+Application_Ledger!K96+14.8 -> 431 | F30: 0 | G30: =D30-E30 -> 0
B31: 21/05/2026 | C31: 2143.25 | D31: =Application_Ledger!J98+Application_Ledger!J99+Application_Ledger!J100+Application_Ledger!J101+Application_Ledger!J102+14.8 -> 732.075 | E31: =Application_Ledger!K98+Application_Ledger!K99+Application_Ledger!K100+Application_Ledger!K101+Application_Ledger!K102+14.8 -> 732.075 | F31: 0 | G31: =D31-E31 -> 0
B32: 22/05/2026 | C32: 2295.25 | D32: =Application_Ledger!J103+Application_Ledger!J104+Application_Ledger!J105+Application_Ledger!J106+Application_Ledger!J107+Application_Ledger!J108 -> 787.6 | E32: =Application_Ledger!K103+Application_Ledger!K104+Application_Ledger!K105+Application_Ledger!K106+Application_Ledger!K107+Application_Ledger!K108 -> 787.6 | F32: 0 | G32: =D32-E32 -> 0
B33: 23/05/2026 | C33: 2295.25 | D33: =Application_Ledger!J109+Application_Ledger!J110+Application_Ledger!J111+Application_Ledger!J112+Application_Ledger!J113+Application_Ledger!J114 -> 858.25 | E33: =Application_Ledger!K109+Application_Ledger!K110+Application_Ledger!K111+Application_Ledger!K112+Application_Ledger!K113+Application_Ledger!K114 -> 858.25 | F33: 0 | G33: =D33-E33 -> 0
B34: 24/05/2026 | C34: 2295.25 | D34: =Application_Ledger!J115+Application_Ledger!J116+Application_Ledger!J117+Application_Ledger!J118+Application_Ledger!J119+14.8 -> 902.3 | E34: =Application_Ledger!K115+Application_Ledger!K116+Application_Ledger!K117+Application_Ledger!K118+Application_Ledger!K119+14.8 -> 902.3 | F34: 0 | G34: =D34-E34 -> 0
B35: 25/05/2026 | C35: 2295.25 | D35: =Application_Ledger!J121+Application_Ledger!J122+Application_Ledger!J123+Application_Ledger!J124+Application_Ledger!J125+14.8 -> 849.4 | E35: =Application_Ledger!K121+Application_Ledger!K122+Application_Ledger!K123+Application_Ledger!K124+Application_Ledger!K125+14.8 -> 849.4 | F35: 0 | G35: =D35-E35 -> 0
B36: 26/05/2026 | C36: 2295.25 | D36: =Application_Ledger!J126+Application_Ledger!J127+Application_Ledger!J128+Application_Ledger!J129+Application_Ledger!J130+14.8 -> 661.075 | E36: =Application_Ledger!K126+Application_Ledger!K127+Application_Ledger!K128+Application_Ledger!K129+Application_Ledger!K130+14.8 -> 661.075 | F36: 0 | G36: =D36-E36 -> 0
B37: 27/05/2026 | C37: 2295.25 | D37: =Application_Ledger!J131+Application_Ledger!J132+Application_Ledger!J133+Application_Ledger!J134+Application_Ledger!J135+14.8 -> 614.725 | E37: =Application_Ledger!K131+Application_Ledger!K132+Application_Ledger!K133+Application_Ledger!K134+Application_Ledger!K135+14.8 -> 614.725 | F37: 0 | G37: =D37-E37 -> 0
B38: 28/05/2026 | C38: 2295.25 | D38: =Application_Ledger!J136+Application_Ledger!J137+Application_Ledger!J138+Application_Ledger!J139+Application_Ledger!J140+14.8 -> 619.2 | E38: =Application_Ledger!K136+Application_Ledger!K137+Application_Ledger!K138+Application_Ledger!K139+Application_Ledger!K140+14.8 -> 619.2 | F38: 0 | G38: =D38-E38 -> 0
B39: 29/05/2026 | C39: 2295.25 | D39: =Application_Ledger!J141+Application_Ledger!J142+Application_Ledger!J143+Application_Ledger!J144+14.8 -> 594.475 | E39: =Application_Ledger!K141+Application_Ledger!K142+Application_Ledger!K143+Application_Ledger!K144+14.8 -> 594.475 | F39: 0 | G39: =D39-E39 -> 0
B40: 30/05/2026 | C40: 2295.25 | D40: =Application_Ledger!J145+Application_Ledger!J146+Application_Ledger!J147+Application_Ledger!J148+Application_Ledger!J149+14.8 -> 671.725 | E40: =Application_Ledger!K145+Application_Ledger!K146+Application_Ledger!K147+Application_Ledger!K148+Application_Ledger!K149+14.8 -> 671.725 | F40: 0 | G40: =D40-E40 -> 0
B41: 31/05/2026 | C41: 2295.25 | D41: =Application_Ledger!J150+Application_Ledger!J151+Application_Ledger!J152+Application_Ledger!J153+Application_Ledger!J154+14.8 -> 790.4 | E41: =Application_Ledger!K150+Application_Ledger!K151+Application_Ledger!K152+Application_Ledger!K153+Application_Ledger!K154+14.8 -> 790.4 | F41: 0 | G41: =D41-E41 -> 0
B42: Monthly Total | C42: =SUM(C11:C41) -> 67960.75 | D42: =SUM(D11:D41) -> 17370.143 | E42: =SUM(E11:E41) -> 17057.018 | F42: =SUM(F11:F41) -> 0 | G42: =SUM(G11:G41) -> 313.125
B43: 46028 | C43: 2295.25 | D43: =Application_Ledger!J156+Application_Ledger!J157+Application_Ledger!J158+Application_Ledger!J159+Application_Ledger!J160 -> 820.525 | E43: =Application_Ledger!K156+Application_Ledger!K157+Application_Ledger!K158+Application_Ledger!K159+Application_Ledger!K160 -> 820.525 | F43: 0 | G43: =D43-E43 -> 0
B44: 46059 | C44: 2295.25 | D44: =Application_Ledger!J161+Application_Ledger!J162+Application_Ledger!J163+Application_Ledger!J164+Application_Ledger!J165 -> 855.275 | E44: =Application_Ledger!K161+Application_Ledger!K162+Application_Ledger!K163+Application_Ledger!K164+Application_Ledger!K165 -> 855.275 | F44: 0 | G44: =D44-E44 -> 0
B45: 46087 | C45: 2295.25 | D45: =Application_Ledger!J166+Application_Ledger!J167+Application_Ledger!J168+Application_Ledger!J169+Application_Ledger!J170 -> 676.15 | E45: =Application_Ledger!K166+Application_Ledger!K167+Application_Ledger!K168+Application_Ledger!K169+Application_Ledger!K170 -> 676.15 | F45: 0 | G45: =D45-E45 -> 0
B46: 46118 | C46: 2295.25 | D46: =Application_Ledger!J171+Application_Ledger!J172+Application_Ledger!J173+Application_Ledger!J174+Application_Ledger!J175 -> 857.6 | E46: =Application_Ledger!K171+Application_Ledger!K172+Application_Ledger!K173+Application_Ledger!K174+Application_Ledger!K175 -> 857.6 | F46: 0 | G46: =D46-E46 -> 0
B47: 46148 | C47: 2295.25 | D47: =Application_Ledger!J176+Application_Ledger!J177+Application_Ledger!J178+Application_Ledger!J179 -> 791.6 | E47: =Application_Ledger!K176+Application_Ledger!K177+Application_Ledger!K178+Application_Ledger!K179 -> 791.6 | F47: 0 | G47: =D47-E47 -> 0
B48: 46179 | C48: 2295.25 | D48: =sum(Application_Ledger!J180:J183) -> 845.0175 | E48: =sum(Application_Ledger!K180:K183) -> 845.0175 | F48: 0 | G48: =D48-E48 -> 0
B49: 46209 | C49: 2295.25 | D49: =Application_Ledger!J184+Application_Ledger!J185+Application_Ledger!J186+Application_Ledger!J187 -> 868.975 | E49: =Application_Ledger!K184+Application_Ledger!K185+Application_Ledger!K186+Application_Ledger!K187 -> 868.975 | F49: 0 | G49: =D49-E49 -> 0
B50: 46240 | C50: 2295.25 | D50: =sum(Application_Ledger!J188:J191) -> 813.4 | E50: =sum(Application_Ledger!K188:K191) -> 813.4 | F50: 0 | G50: =D50-E50 -> 0
B51: 46271 | C51: 2295.25 | D51: =sum(Application_Ledger!J192:J195) -> 923.1 | E51: =sum(Application_Ledger!K192:K195) -> 923.1 | F51: 0 | G51: =D51-E51 -> 0
B52: 46301 | C52: 2295.25 | D52: =sum(Application_Ledger!J196:J199) -> 676.9 | E52: =sum(Application_Ledger!K196:K199) -> 676.9 | F52: 0 | G52: =D52-E52 -> 0
B53: 46332 | C53: 2295.25 | D53: =sum(Application_Ledger!J200:J203) -> 725.6 | E53: =sum(Application_Ledger!K200:K203) -> 725.6 | F53: 0 | G53: =D53-E53 -> 0
B54: 46362 | C54: 2295.25 | D54: =sum(Application_Ledger!J204:J207) -> 907.425 | E54: =sum(Application_Ledger!K204:K207) -> 907.425 | F54: 0 | G54: =D54-E54 -> 0
B55: 13/06/2026 | C55: 2295.25 | D55: =sum(Application_Ledger!J208:J211) -> 1031.75 | E55: =sum(Application_Ledger!K208:K211) -> 1031.75 | F55: 0 | G55: =D55-E55 -> 0
B56: 14/06/2026 | C56: 2295.25 | D56: =sum(Application_Ledger!J212:J215) -> 1105.475 | E56: =sum(Application_Ledger!K212:K215) -> 1105.475 | F56: 0 | G56: =D56-E56 -> 0
B57: 15/06/2026 | C57: 2295.25 | D57: =sum(Application_Ledger!J216:J219) -> 1035.1 | E57: =sum(Application_Ledger!K216:K219) -> 1035.1 | F57: 0 | G57: =D57-E57 -> 0
B58: 16/06/2026 | C58: 2295.25 | D58: =sum(Application_Ledger!J220:J223) -> 1126.775 | E58: =sum(Application_Ledger!K220:K223) -> 1126.775 | F58: 0 | G58: =D58-E58 -> 0
B59: 17/06/2026 | C59: 2295.25 | D59: =sum(Application_Ledger!J224:J227) -> 1020.825 | E59: =sum(Application_Ledger!K224:K227) -> 1020.825 | F59: 0 | G59: =D59-E59 -> 0
B60: 18/06/2026 | C60: 2295.25 | D60: =sum(Application_Ledger!J228:J230) -> 726.125 | E60: =sum(Application_Ledger!K228:K230) -> 726.125 | F60: 0 | G60: =D60-E60 -> 0
B61: 19/06/2026 | C61: 2295.25 | D61: =sum(Application_Ledger!J231:J234) -> 1010.05 | E61: =sum(Application_Ledger!K231:K234) -> 1010.05 | F61: 0 | G61: =D61-E61 -> 0
B62: 20/06/2026 | C62: 2295.25 | D62: =sum(Application_Ledger!J235:J238) -> 1085.85 | E62: =sum(Application_Ledger!K235:K238) -> 1085.85 | F62: 0 | G62: =D62-E62 -> 0
B63: 21/06/2026 | C63: 2295.25 | D63: =sum(Application_Ledger!J239:J243) -> 1311 | E63: =sum(Application_Ledger!K239:K243) -> 1311 | F63: 0 | G63: =D63-E63 -> 0
B64: 22/06/2026 | C64: 2295.25 | D64: =sum(Application_Ledger!J244:J247) -> 1129.375 | E64: =sum(Application_Ledger!K244:K247) -> 1129.375 | F64: 0 | G64: =D64-E64 -> 0
B65: 23/06/2026 | C65: 2295.25 | D65: =sum(Application_Ledger!J248:J252) -> 1088.55 | E65: =sum(Application_Ledger!K248:K252) -> 454.075 | F65: 0 | G65: =D65-E65 -> 634.475
B66: 24/06/2026 | C66: 2295.25 | D66: =sum(Application_Ledger!J253:J257) -> 1143.55 | E66: =sum(Application_Ledger!K253:K257) -> 1143.55 | F66: 0 | G66: =D66-E66 -> 0
B67: 25/06/2026 | C67: 2295.25 | D67: =sum(Application_Ledger!J258:J262) -> 1211.975 | E67: =sum(Application_Ledger!K258:K262) -> 1211.975 | F67: 0 | G67: =D67-E67 -> 0
B68: 26/06/2026 | C68: 2295.25 | D68: =sum(Application_Ledger!J263:J267) -> 1244.9 | E68: =sum(Application_Ledger!K263:K267) -> 1244.9 | F68: 0 | G68: =D68-E68 -> 0
B69: 27/06/2026 | C69: 2295.25 | D69: =sum(Application_Ledger!J268:J272) -> 1247.35 | E69: =sum(Application_Ledger!K268:K272) -> 1247.35 | F69: 0 | G69: =D69-E69 -> 0
B70: 28/06/2026 | C70: 2295.25 | D70: =sum(Application_Ledger!J273:J277) -> 1306.025 | E70: =sum(Application_Ledger!K273:K277) -> 1306.025 | F70: 0 | G70: =D70-E70 -> 0
B71: 29/06/2026 | C71: 2295.25 | D71: =sum(Application_Ledger!J278:J282) -> 1212.15 | E71: =sum(Application_Ledger!K278:K282) -> 1212.15 | F71: 0 | G71: =D71-E71 -> 0
B72: 30/06/2026 | C72: 2295.25 | D72: =sum(Application_Ledger!J283:J287) -> 1140.05 | E72: =sum(Application_Ledger!K283:K287) -> 1140.05 | F72: 0 | G72: =D72-E72 -> 0
B73: Monthly Total | C73: =sum(C43:C72) -> 68857.5 | D73: =sum(D43:D72) -> 29938.443 | E73: =sum(E43:E72) -> 29303.967 | F73: =sum(F43:F72) -> 0 | G73: =sum(G43:G72) -> 634.475
B74: 46029 | C74: 2295.25 | D74: =sum(Application_Ledger!J289:J294) -> 1966.05 | E74: =sum(Application_Ledger!K289:K294) -> 1966.05 | F74: 0 | G74: =D74-E74 -> 0
B75: 46060 | C75: 2295.25 | D75: =sum(Application_Ledger!J295:J300) -> 2104.425 | E75: =sum(Application_Ledger!K295:K300) -> 2104.425 | F75: 0 | G75: =D75-E75 -> 0
B76: 46088 | C76: 2295.25 | D76: =sum(Application_Ledger!J301:J306) -> 2115 | E76: =sum(Application_Ledger!K301:K306) -> 2115 | F76: 0 | G76: =D76-E76 -> 0
B77: 46119 | C77: 2295.25 | D77: =sum(Application_Ledger!J307:J311) -> 2121.075 | E77: =sum(Application_Ledger!K307:K311) -> 2121.075 | F77: 0 | G77: =D77-E77 -> 0
B78: 46149 | C78: 2295.25 | D78: =sum(Application_Ledger!J312:J317) -> 2156.675 | E78: =sum(Application_Ledger!K312:K317) -> 2156.675 | F78: 0 | G78: =D78-E78 -> 0
B79: 46180 | C79: 2295.25 | D79: =sum(Application_Ledger!J318:J323) -> 1976.375 | E79: =sum(Application_Ledger!K318:K323) -> 1976.375 | F79: 0 | G79: =D79-E79 -> 0
B80: 46210 | C80: 2295.25 | D80: =sum(Application_Ledger!J324:J329) -> 1988.525 | E80: =sum(Application_Ledger!K324:K329) -> 1988.525 | F80: 0 | G80: =D80-E80 -> 0
B81: 46241 | C81: 2268.05 | D81: =sum(Application_Ledger!J330:J335) -> 2059.55 | E81: =sum(Application_Ledger!K330:K335) -> 2059.55 | F81: 0 | G81: =D81-E81 -> 0
B82: 46272 | C82: 2268.05 | D82: =sum(Application_Ledger!J336:J341) -> 2024.125 | E82: =sum(Application_Ledger!K336:K341) -> 2024.125 | F82: 0 | G82: =D82-E82 -> 0
B83: 46302 | C83: 2268.05 | D83: =sum(Application_Ledger!J342:J346) -> 1833.05 | E83: =sum(Application_Ledger!K342:K346) -> 1833.05 | F83: 0 | G83: =D83-E83 -> 0
B84: 46333 | C84: 2268.05 | D84: =sum(Application_Ledger!J347:J350) -> 1713.55 | E84: =sum(Application_Ledger!K347:K350) -> 1713.55 | F84: 0 | G84: =D84-E84 -> 0
B85: 46363 | C85: 2268.05 | D85: =sum(Application_Ledger!J351:J354) -> 1766.9 | E85: =sum(Application_Ledger!K351:K354) -> 1766.9 | F85: 0 | G85: =D85-E85 -> 0
B86: 13/07/2026 | C86: 2268.05 | D86: =sum(Application_Ledger!J355:J358) -> 1691.4 | E86: =sum(Application_Ledger!K355:K358) -> 1691.4 | F86: 0 | G86: =D86-E86 -> 0
B87: 14/07/2027 | C87: 2268.05 | D87: =sum(Application_Ledger!J359:J362) -> 1634.4 | E87: =sum(Application_Ledger!K359:K362) -> 1634.4 | F87: 0 | G87: =D87-E87 -> 0
B88: 15/07/2026 | C88: 1822.5 | D88: =sum(Application_Ledger!J363:J366) -> 1570.95 | E88: =sum(Application_Ledger!K363:K366) -> 1570.95 | F88: 0 | G88: =D88-E88 -> 0
B89: 16/07/2026 | C89: 1822.5 | D89: =sum(Application_Ledger!J367:J370) -> 1570.95 | E89: =sum(Application_Ledger!K367:K370) -> 1570.95 | F89: 0 | G89: =D89-E89 -> 0
B90: 17/07/2026 | C90: 1822.5 | D90: =sum(Application_Ledger!J371:J375) -> 1630.1 | E90: =sum(Application_Ledger!K371:K375) -> 1630.1 | F90: 0 | G90: =D90-E90 -> 0
B91: 18/07/2026 | C91: 1822.5 | D91: =sum(Application_Ledger!J376:J380) -> 1542.625 | E91: =sum(Application_Ledger!K376:K380) -> 1542.625 | F91: 0 | G91: =D91-E91 -> 0
B92: 19/07/2026 | C92: 2040.65 | D92: =sum(Application_Ledger!J381:J385) -> 1766.675 | E92: =sum(Application_Ledger!K381:K385) -> 1766.675 | F92: 0 | G92: =D92-E92 -> 0
B93: 20/07/2026 | C93: 2011.9 | D93: =sum(Application_Ledger!J386:J390) -> 1728.1 | E93: =sum(Application_Ledger!K386:K390) -> 1728.1 | F93: 0 | G93: =D93-E93 -> 0
B94: 21/07/2026 | C94: 1814.8 | D94: =sum(Application_Ledger!J391:J395) -> 1559.75 | E94: =sum(Application_Ledger!K391:K395) -> 1559.75 | F94: 0 | G94: =D94-E94 -> 0
B95: 22/07/2026 | C95: 1991.9 | D95: =sum(Application_Ledger!J396:J400) -> 1847.025 | E95: =sum(Application_Ledger!K396:K400) -> 1847.025 | F95: 0 | G95: =D95-E95 -> 0
B96: 23/07/2026 | C96: 2028.15 | D96: =sum(Application_Ledger!J401:J405) -> 1893.4 | E96: =sum(Application_Ledger!K401:K405) -> 1893.4 | F96: 0 | G96: =D96-E96 -> 0
B97: 24/07/2026 | C97: 2028.15 | D97: =sum(Application_Ledger!J406:J411) -> 1905.9 | E97: =sum(Application_Ledger!K406:K411) -> 1905.9 | F97: 0 | G97: =D97-E97 -> 0
B98: 25/07/2026 | C98: 1950.65 | D98: =sum(Application_Ledger!J412:J416) -> 1751.8 | E98: =sum(Application_Ledger!K412:K416) -> 1751.8 | F98: 0 | G98: =D98-E98 -> 0
B99: 26/07/2026 | C99: 1787.92 | D99: =sum(Application_Ledger!J417:J421) -> 1651.875 | E99: 1408.125 | F99: 0 | G99: =D99-E99 -> 243.75
B100: 27/07/2026 | C100: 1674.67 | D100: =sum(Application_Ledger!J422:J426) -> 1549.5 | E100: =sum(Application_Ledger!K422:K426) -> 1549.5 | F100: 0 | G100: =D100-E100 -> 0
...

Sheet Bills received
A1: Invoice Date | B1: Invoice No | C1: CSV | D1: Supply Period from | E1: Supply Period To | F1: Quantum of Power(MWH) | G1: Amount (Rs) | H1: Seller Name | I1: Due date | J1: Amount Paid (Rs.) | K1: Payment Date | L1: Remarks | M1: Net Value after TDS @ 0.1% | N1: TDS Payable | O1: Due Amount (Rs)
A2: 07.04.2026 | B2: 80013546 | C2: Vendor Payable Format 07.04.2026 | D2: 01.04.2026 | E2: 01.04.2026 | F2: 213.75 | G2: 671175 | H2: NTPCREL_PSS1_KPS3_S | I2: 08.04.2026 | J2: =G2-(0.1%*G2) -> 670503.82 | K2: 13.04.2026 | M2: =G2-(0.1%*G2) -> 670503.82 | N2: =G2*0.1% -> 671.175 | O2: =G2-J2-N2 -> 0
A3: 01.05.2026 | B3: 480013612 | C3: Vendor Payable Format 04.05.2026 | D3: 25.04.2026 | E3: 30.04.2026 | F3: 2877.3 | G3: 7897015 | H3: NTPCREL_PSS1_KPS3_S | I3: 02.05.2026 | J3: 7889118 | K3: 04.05.2026 | M3: =round(G3-(0.1%*G3),0) -> 7889118 | N3: =round(G3*0.1%,0) -> 7897 | O3: =G3-J3-N3 -> 0
A4: 09.05.2026 | B4: 480013646 | C4: Vendor Payable Format 10.05.2026 | D4: 01.05.2026 | E4: 08.05.2026 | F4: 3100.125 | G4: 4976090 | H4: NTPCREL_PSS1_KPS3_S | I4: 11.05.2026 | J4: 4971114 | K4: 11.05.2026 | M4: =round(G4-(0.1%*G4),0) -> 4971114 | N4: =round(G4*0.1%,0) -> 4976 | O4: =G4-J4-N4 -> 0
A5: 12.05.2026 | B5: 480013669 | C5: Vendor Payable Format 13.05.2026 | D5: 09.05.2026 | E5: 11.05.2026 | F5: 2242.643 | G5: 3882239 | H5: NTPCREL_PSS1_KPS3_S | I5: 13.05.2026 | J5: 3878357 | K5: 13.05.2026 | M5: =round(G5-(0.1%*G5),0) -> 3878357 | N5: =round(G5*0.1%,0) -> 3882 | O5: =G5-J5-N5 -> 0
A6: 18.05.2026 | B6: 480013690 | C6: Vendor Payable Format 19.05.2026 | D6: 12.05.2026 | E6: 17.05.2026 | F6: 2392.05 | G6: 5633871 | H6: NTPCREL_PSS1_KPS3_S | I6: 19.05.2026 | J6: 5628237 | K6: 19.05.2026 | M6: =round(G6-(0.1%*G6),0) -> 5628237 | N6: =round(G6*0.1%,0) -> 5634 | O6: =G6-J6-N6 -> 0
A7: 25.05.2026 | B7: 480013718 | C7: Vendor Payable Format 26.05.2026 | D7: 18.05.2026 | E7: 24.05.2026 | F7: 4521.2 | G7: 12755507 | H7: NTPCREL_PSS1_KPS3_S | I7: 26.05.2026 | J7: 12742751 | K7: 26.05.2026 | M7: =round(G7-(0.1%*G7),0) -> 12742751 | N7: =round(G7*0.1%,0) -> 12756 | O7: =G7-J7-N7 -> 0
A8: 01.06.2026 | B8: 480013719 | C8: Vendor Payable Format 01.05.2026 | D8: 25.05.2026 | E8: 31.05.2026 | F8: 4801 | G8: 12399840 | H8: NTPCREL_PSS1_KPS3_S | I8: 02.06.2026 | J8: 12387440 | K8: 02.06.2026 | M8: =round(G8-(0.1%*G8),0) -> 12387440 | N8: =round(G8*0.1%,0) -> 12400 | O8: =G8-J8-N8 -> 0
A9: 09.06.2026 | B9: 480013768 | C9: Vendor Payable Format 09.06.2026 | D9: 01.06.2026 | E9: 08.06.2026 | F9: 6528.543 | G9: 16492573 | H9: NTPCREL_PSS1_KPS3_S | I9: 10.06.2026 | J9: 16476080 | K9: 10.06.2026 | M9: =round(G9-(0.1%*G9),0) -> 16476080 | N9: =round(G9*0.1%,0) -> 16493 | O9: =G9-J9-N9 -> 0
A10: 16.06.2026 | B10: 480013792 | C10: Vendor Payable Format 16.06.2026 | D10: 09.06.2026 | E10: 15.06.2026 | F10: 6405.35 | G10: 13573911 | H10: NTPCREL_PSS1_KPS3_S | I10: 17.06.2026 | J10: 13560337 | K10: 19.06.2026 | M10: =round(G10-(0.1%*G10),0) -> 13560337 | N10: =round(G10*0.1%,0) -> 13574 | O10: =G10-J10-N10 -> 0
A11: 24.06.2026 | B11: 480013827 | C11: Vendor Payable Format 24.05.2026 | D11: 16.06.2026 | E11: 23.06.2026 | F11: 7864.075 | G11: 20824094 | H11: NTPCREL_PSS1_KPS3_S | I11: 25.06.2026 | J11: 20803270 | K11: 25.06.2026 | M11: =round(G11-(0.1%*G11),0) -> 20803270 | N11: =round(G11*0.1%,0) -> 20824 | O11: =G11-J11-N11 -> 0
A12: 01.07.2026 | B12: 480013878 | C12: Vendor Payable Format 01.07.2026 | D12: 24.06.2026 | E12: 30.06.2026 | F12: 8506 | G12: 20514075 | H12: NTPCREL_PSS1_KPS3_S | I12: 02.07.2026 | J12: 20493561 | K12: 02.07.2026 | M12: =round(G12-(0.1%*G12),0) -> 20493561 | N12: =round(G12*0.1%,0) -> 20514 | O12: =G12-J12-N12 -> 0

Sheet Bills issued by SJVN
A1: Invoice Date | B1: Invoice No | C1: Invoice Type | D1: Supply Period from | E1: Supply Period To | F1: Amount | G1: Party Name | H1: Payment Due date | I1: Payment Received | J1: Date of Payment | K1: Invoice after 0.1% TDS Deduction | L1: TDS Value @ 0.1% | M1: balance | N1: Remarks
A2: 04.05.2026 | B2: SJVN/ENERGY/KREATE/202605/144 | C2: Energy Bill | D2: 01.04.2026 | E2: 30.04.2026 | F2: 8660920 | G2: KREATE | H2: 05.05.2026 | I2: =8652189+5070 -> 8657259 | J2: Payment Recevied on next day of scheduling of power | K2: =ROUND(F2-(0.1%*F2),0) -> 8652259 | L2: =ROUND(F2*0.1%,0) -> 8661 | M2: =F2-I2-L2 -> -5000
A3: 04.05.2026 | B3: SJVN/OA/KREATE/202605/263 | C3: OA Bill | D3: 25.04.2026 | E3: 30.04.2026 | F3: 1212991 | G3: KREATE | H3: 05.05.2026 | I3: 1212991 | J3: 06.05.2026 | K3: 1212991 | L3: 0 | M3: =F3-I3-L3 -> 0
A4: 02.06.2026 | B4: SJVN/ENERGY/KREATE/202606/145 | C4: Energy Bill | D4: 01.05.2026 | E4: 31.05.2026 | F4: 40159255 | G4: KREATE | H4: 03.06.2026 | I4: 40119731 | J4: Payment Recevied on next day of scheduling of power | K4: =ROUND(F4-(0.1%*F4),0) -> 40119096 | L4: =ROUND(F4*0.1%,0) -> 40159 | M4: =F4-I4-L4 -> -635
A5: 11.05.2026 | B5: SJVN/OA/KREATE/202605/264 | C5: OA Bill | D5: 01.05.2026 | E5: 08.05.2026 | F5: 1224379 | G5: KREATE | H5: 12.05.2026 | I5: 1224379 | J5: 12.05.2026 | K5: 1224379 | L5: 0 | M5: =F5-I5-L5 -> 0
A6: 18.05.2026 | B6: SJVN/OA/KREATE/202605/265 | C6: OA Bill | D6: 09.05.2026 | E6: 15.05.2026 | F6: 1340100 | G6: KREATE | H6: 19.05.2026 | I6: 1340100 | J6: 19.05.2026 | K6: 1340100 | L6: 0 | M6: =F6-I6-L6 -> 0
A7: 27.05.2026 | B7: SJVN/OA/KREATE/202605/266 | C7: OA Bill | D7: 16.05.2026 | E7: 23.05.2026 | F7: 1961911 | G7: KREATE | H7: 28.05.2026 | I7: 1961911 | J7: 02.06.2026 | K7: 1961911 | L7: 0 | M7: =F7-I7-L7 -> 0
A8: 01.06.2026 | B8: SJVN/OA/KREATE/202606/267 | C8: OA Bill | D8: 24.05.2026 | E8: 31.05.2026 | F8: 2386581 | G8: KREATE | H8: 02.06.2026 | I8: 2386581 | J8: 03.06.2026 | K8: 2386581 | L8: 0 | M8: =F8-I8-L8 -> 0
A9: 04.06.2026 | B9: SJVN/OA/KREATE/202606/268 | C9: OA Bill | D9: 01.06.2026 | E9: 03.06.2026 | F9: 934820 | G9: KREATE | H9: 04.06.2026 | I9: 934820 | J9: Payment Recevied on Daily Basis | K9: 934820 | L9: 0 | M9: 0
A10: 01.07.2026 | B10: SJVN/ENERGY/KREATE/202607/146 | C10: Energy Bill | D10: 01.06.2026 | E10: 30.06.2026 | F10: 72283771 | G10: KREATE | H10: 02.07.2026 | I10: 72219123 | J10: Payment Recevied on next day of scheduling of power | K10: =ROUND(F10-(0.1%*F10),0) -> 72211487 | L10: =ROUND(F10*0.1%,0) -> 72284 | M10: =F10-I10-L10 -> -7636
A11: 01.07.2026 | B11: SJVN/OA/KREATE/202606/269 | C11: OA Bill | D11: 04.06.2026 | E11: 30.06.2026 | F11: 10708005 | G11: KREATE | H11: 02.07.2026 | I11: 10708005 | J11: Payment Recevied on Daily Basis | K11: 10708005 | L11: 0 | M11: 0

Sheet May TDS 2026
A1: Ref No | B1: Application No | C1: Approval No | D1: Party Name | E1: PAN | F1: Taxable Amount | G1: TDS Rate (%) | H1: TDS | I1: Remarks
A2: 160469 | B2: SJVN010526WR2374 | C2: WR/2026/42914/C/R/0 | D2: CTUIL | E2: AAJCC2026N | F2: 97111 | G2: 0.1 | H2: =ROUND(F2*G2,0) -> 9711 | I2: =F2-H2 -> 87400
A3: 160469 | B3: SJVN010526WR2374 | C3: WR/2026/42914/C/R/0 | D3: GRID-INDIA | E3: AAFCP2086B | F3: 5000 | G3: 0.1 | H3: =ROUND(F3*G3,0) -> 500 | I3: =F3-H3 -> 4500
A4: 160469 | B4: SJVN010526WR2374 | C4: WR/2026/42914/C/R/0 | D4: RLDC-Fee | E4: AAFCP2086B | F4: 1000 | G4: 0.1 | H4: =ROUND(F4*G4,0) -> 100 | I4: =F4-H4 -> 900
A5: 160475 | B5: SJVN010526WR2376 | C5: WR/2026/42916/C/R/0 | D5: CTUIL | E5: AAJCC2026N | F5: 17555 | G5: 0.1 | H5: =ROUND(F5*G5,0) -> 1756 | I5: =F5-H5 -> 15799
A6: 160475 | B6: SJVN010526WR2376 | C6: WR/2026/42916/C/R/0 | D6: GRID-INDIA | E6: AAFCP2086B | F6: 5000 | G6: 0.1 | H6: =ROUND(F6*G6,0) -> 500 | I6: =F6-H6 -> 4500
A7: 160475 | B7: SJVN010526WR2376 | C7: WR/2026/42916/C/R/0 | D7: RLDC-Fee | E7: AAFCP2086B | F7: 1000 | G7: 0.1 | H7: =ROUND(F7*G7,0) -> 100 | I7: =F7-H7 -> 900
A8: 160478 | B8: SJVN010526WR2377 | C8: WR/2026/42918/C/R/0 | D8: CTUIL | E8: AAJCC2026N | F8: 45644 | G8: 0.1 | H8: =ROUND(F8*G8,0) -> 4564 | I8: =F8-H8 -> 41080
A9: 160478 | B9: SJVN010526WR2377 | C9: WR/2026/42918/C/R/0 | D9: GRID-INDIA | E9: AAFCP2086B | F9: 5000 | G9: 0.1 | H9: =ROUND(F9*G9,0) -> 500 | I9: =F9-H9 -> 4500
A10: 160478 | B10: SJVN010526WR2377 | C10: WR/2026/42918/C/R/0 | D10: RLDC-Fee | E10: AAFCP2086B | F10: 1000 | G10: 0.1 | H10: =ROUND(F10*G10,0) -> 100 | I10: =F10-H10 -> 900
A11: 160482 | B11: SJVN010526ER2378 | C11: ER/2026/28089/C/R/0 | D11: CTUIL | E11: AAJCC2026N | F11: 8485 | G11: 0.1 | H11: =ROUND(F11*G11,0) -> 849 | I11: =F11-H11 -> 7636
A12: 160482 | B12: SJVN010526ER2378 | C12: ER/2026/28089/C/R/0 | D12: GRID-INDIA | E12: AAFCP2086B | F12: 5000 | G12: 0.1 | H12: =ROUND(F12*G12,0) -> 500 | I12: =F12-H12 -> 4500
A13: 160482 | B13: SJVN010526ER2378 | C13: ER/2026/28089/C/R/0 | D13: RLDC-Fee | E13: AAFCP2086B | F13: 1000 | G13: 0.1 | H13: =ROUND(F13*G13,0) -> 100 | I13: =F13-H13 -> 900
... A64: 161880 | B64: SJVN090526WR2397 | C64: WR/2026/43380/C/R/0 | D64: RLDC-Fee | E64: AAFCP2086B | F64: 1000 | G64: 0.1 | H64: =ROUND(F64*G64,0) -> 100 | I64: =F64-H64 -> 900
D65: CTUIL | E65: AAJCC2026N | G65: 0.1 | H65: =ROUND(F65*G65,0) -> 0 | I65: =F65-H65 -> 0
D66: GRID-INDIA | E66: AAFCP2086B | F66: 5000 | G66: 0.1 | H66: =ROUND(F66*G66,0) -> 500 | I66: =F66-H66 -> 4500
D67: RLDC-Fee | E67: AAFCP2086B | F67: 1000 | G67: 0.1 | H67: =ROUND(F67*G67,0) -> 100 | I67: =F67-H67 -> 900
D68: CTUIL | E68: AAJCC2026N | G68: 0.1 | H68: =ROUND(F68*G68,0) -> 0 | I68: =F68-H68 -> 0
D69: GRID-INDIA | E69: AAFCP2086B | F69: 5000 | G69: 0.1 | H69: =ROUND(F69*G69,0) -> 500 | I69: =F69-H69 -> 4500
D70: RLDC-Fee | E70: AAFCP2086B | F70: 1000 | G70: 0.1 | H70: =ROUND(F70*G70,0) -> 100 | I70: =F70-H70 -> 900
D71: CTUIL | E71: AAJCC2026N | G71: 0.1 | H71: =ROUND(F71*G71,0) -> 0 | I71: =F71-H71 -> 0
D72: GRID-INDIA | E72: AAFCP2086B | F72: 5000 | G72: 0.1 | H72: =ROUND(F72*G72,0) -> 500 | I72: =F72-H72 -> 4500
D73: RLDC-Fee | E73: AAFCP2086B | F73: 1000 | G73: 0.1 | H73: =ROUND(F73*G73,0) -> 100 | I73: =F73-H73 -> 900
D74: CTUIL | E74: AAJCC2026N | G74: 0.1 | H74: =ROUND(F74*G74,0) -> 0 | I74: =F74-H74 -> 0
D75: GRID-INDIA | E75: AAFCP2086B | F75: 5000 | G75: 0.1 | H75: =ROUND(F75*G75,0) -> 500 | I75: =F75-H75 -> 4500
D76: RLDC-Fee | E76: AAFCP2086B | F76: 1000 | G76: 0.1 | H76: =ROUND(F76*G76,0) -> 100 | I76: =F76-H76 -> 900
D77: CTUIL | E77: AAJCC2026N | G77: 0.1 | H77: =ROUND(F77*G77,0) -> 0 | I77: =F77-H77 -> 0
D78: GRID-INDIA | E78: AAFCP2086B | F78: 5000 | G78: 0.1 | H78: =ROUND(F78*G78,0) -> 500 | I78: =F78-H78 -> 4500
D79: RLDC-Fee | E79: AAFCP2086B | F79: 1000 | G79: 0.1 | H79: =ROUND(F79*G79,0) -> 100 | I79: =F79-H79 -> 900
D80: CTUIL | E80: AAJCC2026N | G80: 0.1 | H80: =ROUND(F80*G80,0) -> 0 | I80: =F80-H80 -> 0
D81: GRID-INDIA | E81: AAFCP2086B | F81: 5000 | G81: 0.1 | H81: =ROUND(F81*G81,0) -> 500 | I81: =F81-H81 -> 4500
D82: RLDC-Fee | E82: AAFCP2086B | F82: 1000 | G82: 0.1 | H82: =ROUND(F82*G82,0) -> 100 | I82: =F82-H82 -> 900
D83: CTUIL | E83: AAJCC2026N | G83: 0.1 | H83: =ROUND(F83*G83,0) -> 0 | I83: =F83-H83 -> 0
D84: GRID-INDIA | E84: AAFCP2086B | F84: 5000 | G84: 0.1 | H84: =ROUND(F84*G84,0) -> 500 | I84: =F84-H84 -> 4500
D85: RLDC-Fee | E85: AAFCP2086B | F85: 1000 | G85: 0.1 | H85: =ROUND(F85*G85,0) -> 100 | I85: =F85-H85 -> 900
D86: CTUIL | E86: AAJCC2026N | G86: 0.1 | H86: =ROUND(F86*G86,0) -> 0 | I86: =F86-H86 -> 0
D87: GRID-INDIA | E87: AAFCP2086B | F87: 5000 | G87: 0.1 | H87: =ROUND(F87*G87,0) -> 500 | I87: =F87-H87 -> 4500
D88: RLDC-Fee | E88: AAFCP2086B | F88: 1000 | G88: 0.1 | H88: =ROUND(F88*G88,0) -> 100 | I88: =F88-H88 -> 900

Sheet April TDS 2026
A1: Ref No | B1: Application No | C1: Approval No | D1: Party Name | E1: PAN | F1: Taxable Amount | G1: TDS Rate (%) | H1: TDS | I1: Remarks
A2: 154714 | B2: SJVN010426WR2354 | C2: WR/2026/41024/C/R/0 | D2: CTUIL | E2: AAJCC2026N | F2: 80568 | G2: 0.1 | H2: =ROUND(F2*G2,0) -> 8057 | I2: =F2-H2 -> 72511
A3: 154714 | B3: SJVN010426WR2354 | C3: WR/2026/41024/C/R/0 | D3: GRID-INDIA | E3: AAFCP2086B | F3: 5000 | G3: 0.1 | H3: =ROUND(F3*G3,0) -> 500 | I3: =F3-H3 -> 4500
A4: 154714 | B4: SJVN010426WR2354 | C4: WR/2026/41024/C/R/0 | D4: RLDC-Fee | E4: AAFCP2086B | F4: 1000 | G4: 0.1 | H4: =ROUND(F4*G4,0) -> 100 | I4: =F4-H4 -> 900
A5: 154718 | B5: SJVN010426WR2355 | C5: WR/2026/41026/C/R/0 | D5: CTUIL | E5: AAJCC2026N | F5: 3051 | G5: 0.1 | H5: =ROUND(F5*G5,0) -> 305 | I5: =F5-H5 -> 2746
A6: 154718 | B6: SJVN010426WR2355 | C6: WR/2026/41026/C/R/0 | D6: GRID-INDIA | E6: AAFCP2086B | F6: 5000 | G6: 0.1 | H6: =ROUND(F6*G6,0) -> 500 | I6: =F6-H6 -> 4500
A7: 154718 | B7: SJVN010426WR2355 | C7: WR/2026/41026/C/R/0 | D7: RLDC-Fee | E7: AAFCP2086B | F7: 1000 | G7: 0.1 | H7: =ROUND(F7*G7,0) -> 100 | I7: =F7-H7 -> 900
A8: 158826 | B8: SJVN250426WR2356 | C8: WR/2026/42379/C/R/0 | D8: CTUIL | E8: AAJCC2026N | F8: 84255 | G8: 0.1 | H8: =ROUND(F8*G8,0) -> 8426 | I8: =F8-H8 -> 75829
A9: 158826 | B9: SJVN250426WR2356 | C9: WR/2026/42379/C/R/0 | D9: GRID-INDIA | E9: AAFCP2086B | F9: 5000 | G9: 0.1 | H9: =ROUND(F9*G9,0) -> 500 | I9: =F9-H9 -> 4500
A10: 158826 | B10: SJVN250426WR2356 | C10: WR/2026/42379/C/R/0 | D10: RLDC-Fee | E10: AAFCP2086B | F10: 1000 | G10: 0.1 | H10: =ROUND(F10*G10,0) -> 100 | I10: =F10-H10 -> 900
A11: 159167 | B11: SJVN260426WR2357 | C11: WR/2026/42484/C/R/0 | D11: CTUIL | E11: AAJCC2026N | F11: 52812 | G11: 0.1 | H11: =ROUND(F11*G11,0) -> 5281 | I11: =F11-H11 -> 47531
A12: 159167 | B12: SJVN260426WR2357 | C12: WR/2026/42484/C/R/0 | D12: GRID-INDIA | E12: AAFCP2086B | F12: 5000 | G12: 0.1 | H12: =ROUND(F12*G12,0) -> 500 | I12: =F12-H12 -> 4500
A13: 159167 | B13: SJVN260426WR2357 | C13: WR/2026/42484/C/R/0 | D13: RLDC-Fee | E13: AAFCP2086B | F13: 1000 | G13: 0.1 | H13: =ROUND(F13*G13,0) -> 100 | I13: =F13-H13 -> 900
... A52: 160246 | B52: SJVN300426WR2373 | C52: WR/2026/42851/C/R/0 | D52: RLDC-Fee | E52: AAFCP2086B | F52: 1000 | G52: 0.1 | H52: =ROUND(F52*G52,0) -> 100 | I52: =F52-H52 -> 900

Sheet OPEN ACCESS PAYMENT AND APPROVE
A1: Delivary Date | B1: Application No | C1: Amount | E1: Payment Received
A2: 46028 | B2: SJVN010626WR2523 | C2: 118061 | E2: Received Date | F2: Amount Received
A3: 46028 | B3: SJVN010626WR2524 | C3: 102912 | E3: 46118 | F3: 324732
A4: 46028 | B4: SJVN010626WR2525 | C4: 18572
A5: 46028 | B5: SJVN010626WR2526 | C5: 48026
A6: 46028 | B6: SJVN010626WR2527 | C6: 37161
B7: Total | C7: 324732
A8: Delivary Date | B8: Application No | C8: Amount | E8: 46118 | F8: 337215
A9: 46059 | B9: SJVN020626WR2528 | C9: 125694
A10: 46059 | B10: SJVN020626WR2529 | C10: 109737
A11: 46059 | B11: SJVN020626WR2530 | C11: 18572
A12: 46059 | B12: SJVN020626WR2531 | C12: 41561
A13: 46059 | B13: SJVN020626WR2532 | C13: 41651
B14: Total | C14: 337215
A15: Delivary Date | B15: Application No | C15: Amount
A16: 46087 | B16: SJVN030626WR2534 | C16: 20727 | E16: 46118 | F16: 272873
A17: 46087 | B17: SJVN030626WR2535 | C17: 46500
A18: 46087 | B18: SJVN030626WR2536 | C18: 17225
A19: 46087 | B19: SJVN030626WR2537 | C19: 85509
A20: 46087 | B20: SJVN030626WR2538 | C20: 102912
B21: Total | C21: 272873
A22: Delivary Date | B22: Application No | C22: Amount
A23: 46118 | B23: SJVN040626WR2539 | C23: 107690 | E23: 46148 | F23: 338,051.00
A24: 46118 | B24: SJVN040626WR2540 | C24: 123279
A25: 46118 | B25: SJVN040626WR2541 | C25: 20368
A26: 46118 | B26: SJVN040626WR2542 | C26: 52696
A27: 46118 | B27: SJVN040626WR2543 | C27: 34018
B28: Total | C28: 338051
A29: Delivary Date | B29: Application No | C29: Amount
A30: 46148 | B30: SJVN050626WR2544 | C30: 107690 | E30: 46179 | F30: 308343
A31: 46148 | B31: SJVN050626WR2545 | C31: 123279
A32: 46148 | B32: SJVN050626WR2546 | C32: 49104
A33: 46148 | B33: SJVN050626WR2547 | C33: 28270
B34: Total | C34: 308343
A35: Delivary Date | B35: Application No | C35: Amount
A36: 46179 | B36: SJVN060626WR2548 | C36: 89790 | E36: 46240 | F36: 327530
A37: 46179 | B37: SJVN060626WR2549 | C37: 127050
A38: 46179 | B38: SJVN060626WR2550 | C38: 46949
A39: 46179 | B39: SJVN060626WR2551 | C39: 63741
B40: Total | C40: 327530
A41: Delivary Date | B41: Application No | C41: Amount
A42: 46209 | B42: SJVN070626WR2552 | C42: 102768 | E42: 46240 | F42: 336135
A43: 46209 | B43: SJVN070626WR2553 | C43: 134234
A44: 46209 | B44: SJVN070626WR2554 | C44: 52274
A45: 46209 | B45: SJVN070626WR2555 | C45: 46859
B46: Total | C46: 336135
A47: Delivary Date | B47: Application No | C47: Amount
A48: 46240 | B48: SJVN080626WR2556 | C48: 94597 | E48: 46271 | F48: 316174
A49: 46240 | B49: SJVN080626WR2557 | C49: 127769
A50: 46240 | B50: SJVN080626WR2558 | C50: 50182
A51: 46240 | B51: SJVN080626WR2559 | C51: 43626
B52: Total | C52: 316174
A53: Delivary Date | B53: Application No | C53: Amount
A54: 46271 | B54: SJVN090626WR2560 | C54: 112988 | E54: 46301 | F54: 355578
A55: 46271 | B55: SJVN090626WR2561 | C55: 127769
A56: 46271 | B56: SJVN090626WR2562 | C56: 50182
A57: 46271 | B57: SJVN090626WR2563 | C57: 64639
B58: Total | C58: =SUM(C54:C57) -> 355578
A60: Delivary Date | B60: Application No | C60: Amount | E60: 46332 | F60: 267142
A61: 46301 | B61: SJVN100626WR2564 | C61: 109144
A62: 46301 | B62: SJVN100626WR2565 | C62: 65268
A63: 46301 | B63: SJVN100626WR2566 | C63: 28091
A64: 46301 | B64: SJVN100626WR2567 | C64: 64639
B65: Total | C65: 267142
A67: Delivary Date | B67: Application No | C67: Amount | E67: 46332 | F67: 284635
A68: 46332 | B68: SJVN110626WR2568 | C68: 100865
A69: 46332 | B69: SJVN110626WR2569 | C69: 65268
A70: 46332 | B70: SJVN110626WR2570 | C70: 53863
A71: 46332 | B71: SJVN110626WR2571 | C71: 64639
B72: Total | C72: 284635
A74: Delivary Date | B74: Application No | C74: Amount
A75: 46362 | B75: SJVN120626WR2572 | C75: 100757 | E75: 46362 | F75: 349947
A76: 46362 | B76: SJVN120626WR2573 | C76: 131361
A77: 46362 | B77: SJVN120626WR2574 | C77: 55704
A78: 46362 | B78: SJVN120626WR2576 | C78: 62125
B79: Total | C79: 349947
A81: Delivary Date | B81: Application No | C81: Amount
A82: 13-06-2026 | B82: SJVN130626WR2577 | C82: 120675 | E82: 15/06/2026 | F82: 394605
A83: 13-06-2026 | B83: SJVN130626WR2578 | C83: 141239
A84: 13-06-2026 | B84: SJVN130626WR2579 | C84: 59341
A85: 13-06-2026 | B85: SJVN130626WR2580 | C85: 73350
B86: Total | C86: 394605
A88: Delivary Date | B88: Application No | C88: Amount | E88: 15-06-2026 | F88: 421086
A89: 14-06-2026 | B89: SJVN140626WR2581 | C89: 132941
A90: 14-06-2026 | B90: SJVN140626WR2582 | C90: 146393
A91: 14-06-2026 | B91: SJVN140626WR2583 | C91: 59341
A92: 14-06-2026 | B92: SJVN140626WR2584 | C92: 82411
B93: Total | C93: 421086
A95: Delivary Date | B95: Application No | C95: Amount | E95: 15-06-2026 | F95: 395808
A96: 15-06-2026 | B96: SJVN150626WR2585 | C96: 131855
A97: 15-06-2026 | B97: SJVN150626WR2586 | C97: 134315
A98: 15-06-2026 | B98: SJVN150626WR2587 | C98: 59341
A99: 15-06-2026 | B99: SJVN150626WR2588 | C99: 70297
B100: Total | C100: =SUM(C96:C99) -> 395808
A102: Delivary Date | B102: Application No | C102: Amount
A103: 16-06-2026 | B103: SJVN160626WR2589 | C103: 136776 | E103: 16-06-2026 | F103: 428739
A104: 16-06-2026 | B104: SJVN160626WR2590 | C104: 160573
A105: 16-06-2026 | B105: SJVN160626WR2591 | C105: 60554
A106: 16-06-2026 | B106: SJVN160626WR2592 | C106: 70836
B107: Total | C107: =SUM(C103:C106) -> 428739
...

Sheet ENERGY PAYMENT 
A1: Sl. No | B1: Date | C1: Energy (KWh) | D1: Rate | E1: Amount | F1: TDS | G1: Cumulative Amount | H1: Payment made | I1: Payment date | J1: Payment due | K1: Bill No | L1: Bill date | M1: Energy | N1: Rate | O1: Amount | P1: TDS | Q1: TDS DEDUCTED | R1: Net Receivable | S1: Actual Receipt | T1: Difference | U1: Date of Receipt
A2: 46138
B3: 46026 | C3: 213750 | D3: 3.14 | E3: 671175 | F3: 6711.75 | G3: 664463.25 | M3: 213750 | N3: 3.17 | O3: 677587.5 | P3: 677.5875 | R3: 676909.91 | S3: 677587 | T3: 677.0875 | U3: 46269
B4: 25-04-2026 | C4: 215375 | D4: 2.956 | E4: 636649 | F4: 6366.49 | G4: 630282.51 | M4: 215375 | N4: 2.986 | O4: 643109.75 | P4: 643.10975 | R4: 642466.64 | S4: 642564 | T4: 97.35975 | U4: 27/04/2026
B5: 26-04-2026 | C5: 246925 | D5: 2.727 | E5: 673365 | F5: 6733.65 | G5: 666631.35 | M5: 246925 | N5: 2.757 | O5: 680772.23 | P5: 680.77223 | R5: 680091.46 | S5: 680214 | T5: 122.54223 | U5: 27/04/2026
B6: 27-04-2027 | C6: 590500 | D6: 2.688 | E6: 1587264 | F6: 15872.64 | G6: 1571391.4 | M6: 590500 | N6: 2.718 | O6: 1604979 | P6: 1604.979 | R6: 1603374 | S6: 1603590 | T6: 215.979 | U6: 27/04/2026
B7: 28-04-2026 | C7: 655500 | D7: 3.049 | E7: 1998620 | F7: 19986.2 | G7: 1978633.8 | M7: 655500 | N7: 3.079 | O7: 2018284.5 | P7: 2018.2845 | R7: 2016266.2 | S7: 2016103 | T7: -163.2155 | U7: 29-04-2026
B8: 29-04-2026 | C8: 630000 | D8: 2.588 | E8: 1630440 | F8: 16304.4 | G8: 1614135.6 | M8: 630000 | N8: 2.618 | O8: 1649340 | P8: 1649.34 | R8: 1647690.7 | S8: 1647840 | T8: 149.34 | U8: 30-04-2026
B9: 30-04-2026 | C9: 539000 | D9: 2.543 | E9: 1370677 | F9: 13706.77 | G9: 1356970.2 | M9: 539000 | N9: 2.573 | O9: 1386847 | P9: 1386.847 | R9: 1385460.2 | S9: 1384291 | T9: -1169.153 | U9: 46058
K10: Remaining amount for the supply of power for the month of april-26 & TDS is applicable above Rs. 5000000 | S10: 5070 | T10: 5070 | U10: 46178
B11: Total | C11: 3091050 | E11: 8568190 | F11: 85681.9 | G11: 8482508.1 | H11: 0 | I11: 0 | J11: 0 | M11: 3091050 | O11: 8660920 | P11: 8660.92 | R11: 8652259.1 | S11: 8652189 | T11: 4999.94
A12: 46168
A13: 1 | B13: 46027 | C13: 4,31,175 | D13: 1.913 | E13: 8,24,838.00 | F13: 825 | G13: 8,24,013.00 | K13: 1 | L13: 46027 | M13: 4,31,175 | N13: 1.943 | O13: 8,37,773.03 | P13: 837.77 | R13: 8,36,935.25 | S13: 8,37,138.00 | T13: 202.75 | U13: 46058
A14: 2 | B14: 46058 | C14: 3,15,625 | D14: 1.56 | E14: 4,92,375.00 | F14: 492 | G14: 4,91,883.00 | K14: 2 | L14: 46058 | M14: 3,15,625 | N14: 1.59 | O14: 5,01,843.75 | P14: 501.84 | R14: 5,01,341.91 | S14: 5,01,326.00 | T14: -15.91 | U14: 46117
A15: 3 | B15: 46086 | C15: 4,70,475 | D15: 1.205 | E15: 5,66,922.00 | F15: 567 | G15: 5,66,355.00 | K15: 3 | L15: 46086 | M15: 4,70,475 | N15: 1.235 | O15: 5,81,036.63 | P15: 581.04 | R15: 5,80,455.59 | S15: 5,80,662.00 | T15: 206.41 | U15: 46117
A16: 4 | B16: 46117 | C16: 2,22,100 | D16: 1.184 | E16: 2,62,966.00 | F16: 263 | G16: 2,62,703.00 | K16: 4 | L16: 46117 | M16: 2,22,100 | N16: 1.214 | O16: 2,69,629.40 | P16: 269.63 | R16: 2,69,359.77 | S16: 2,69,248.00 | T16: -111.77 | U16: 46147
A17: 5 | B17: 46147 | C17: 2,39,600 | D17: 1.53 | E17: 3,66,588.00 | F17: 367 | G17: 3,66,221.00 | K17: 5 | L17: 46147 | M17: 2,39,600 | N17: 1.56 | O17: 3,73,776.00 | P17: 373.78 | R17: 3,73,402.22 | S17: 3,73,515.00 | T17: 112.78 | U17: 46178
A18: 6 | B18: 46178 | C18: 3,30,725 | D18: 1.593 | E18: 5,26,845.00 | F18: 527 | G18: 5,26,318.00 | K18: 6 | L18: 46178 | M18: 3,30,725 | N18: 1.623 | O18: 5,36,766.68 | P18: 536.77 | R18: 5,36,229.91 | S18: 5,36,303.00 | T18: 73.09 | U18: 46208
A19: 7 | B19: 46208 | C19: 3,41,400 | D19: 1.83 | E19: 6,24,762.00 | F19: 625 | G19: 6,24,137.00 | K19: 7 | L19: 46208 | M19: 3,41,400 | N19: 1.86 | O19: 6,35,004.00 | P19: 635 | R19: 6,34,369.00 | S19: 6,34,288.00 | T19: -81 | U19: 46239
A20: 8 | B20: 46239 | C20: 7,49,025 | D20: 1.75 | E20: 13,10,794.00 | F20: 1311 | G20: 13,09,483.00 | K20: 8 | L20: 46239 | M20: 7,49,025 | N20: 1.78 | O20: 13,33,264.50 | P20: 1333.26 | R20: 13,31,931.24 | S20: 13,32,285.00 | T20: 353.76 | U20: 11.05.2026
A21: 9 | B21: 46270 | C21: 7,66,205 | D21: 1.989 | E21: 15,23,982.00 | F21: 1524 | G21: 15,22,458.00 | K21: 9 | L21: 46270 | M21: 7,66,205 | N21: 2.019 | O21: 15,46,967.90 | P21: 1546.97 | R21: 15,45,420.93 | S21: 15,45,083.00 | T21: -337.93 | U21: 11.05.2026
A22: 10 | B22: 46300 | C22: 9,16,588 | D22: 1.551 | E22: 14,21,628.00 | F22: 1422 | G22: 14,20,206.00 | K22: 10 | L22: 46300 | M22: 9,16,588 | N22: 1.581 | O22: 14,49,125.63 | P22: 1449.13 | R22: 14,47,676.50 | S22: 14,47,289.00 | T22: -387.5 | U22: 11.05.2026
A23: 11 | B23: 46331 | C23: 5,59,850 | D23: 1.673 | E23: 9,36,629.00 | F23: 937 | G23: 9,35,692.00 | K23: 11 | L23: 46331 | M23: 5,59,850 | N23: 1.703 | O23: 9,53,424.55 | P23: 953.42 | R23: 9,52,471.13 | S23: 9,52,591.00 | T23: 119.87 | U23: 12.05.2026
A24: 12 | B24: 46361 | C24: 6,92,650 | D24: 2.178 | E24: 15,08,592.00 | F24: 1509 | G24: 15,07,083.00 | K24: 12 | L24: 46361 | M24: 6,92,650 | N24: 2.208 | O24: 15,29,371.20 | P24: 1529.37 | R24: 15,27,841.83 | S24: 15,27,951.00 | T24: 109.17 | U24: 13.05.2026
A25: 13 | B25: 13-05-2026 | C25: 3,92,425 | D25: 2.208 | E25: 8,66,474.00 | F25: 866 | G25: 8,65,608.00 | K25: 13 | L25: 13-05-2026 | M25: 3,92,425 | N25: 2.238 | O25: 8,78,247.15 | P25: 878.25 | R25: 8,77,368.90 | S25: 8,77,480.00 | T25: 111.1 | U25: 14.05.2026
A26: 14 | B26: 14-05-2026 | C26: 2,21,900 | D26: 2.393 | E26: 5,31,007.00 | F26: 531 | G26: 5,30,476.00 | K26: 14 | L26: 14-05-2026 | M26: 2,21,900 | N26: 2.423 | O26: 5,37,663.70 | P26: 537.66 | R26: 5,37,126.04 | S26: 5,37,036.00 | T26: -90.04 | U26: 15.05.2026
A27: 15 | B27: 15-05-2026 | C27: 3,76,975 | D27: 2.56 | E27: 9,65,056.00 | F27: 965 | G27: 9,64,091.00 | K27: 15 | L27: 15-05-2026 | M27: 3,76,975 | N27: 2.59 | O27: 9,76,365.25 | P27: 976.37 | R27: 9,75,388.88 | S27: 9,75,553.00 | T27: 164.12 | U27: 16.05.2026
A28: 16 | B28: 16-05-2026 | C28: 3,14,850 | D28: 2.671 | E28: 8,40,964.00 | F28: 841 | G28: 8,40,123.00 | K28: 16 | L28: 16-05-2026 | M28: 3,14,850 | N28: 2.701 | O28: 8,50,409.85 | P28: 850.41 | R28: 8,49,559.44 | S28: 8,49,626.00 | T28: 66.56 | U28: 17.05.2026
A29: 17 | B29: 17-05-2026 | C29: 3,93,250 | D29: 2.344 | E29: 9,21,778.00 | F29: 922 | G29: 9,20,856.00 | K29: 17 | L29: 17-05-2026 | M29: 3,93,250 | N29: 2.374 | O29: 9,33,575.50 | P29: 933.58 | R29: 9,32,641.92 | S29: 9,32,657.00 | T29: 15.08 | U29: 17.05.2026
A30: 18 | B30: 18-05-2026 | C30: 4,35,975 | D30: 3.133 | E30: 13,65,910.00 | F30: 1366 | G30: 13,64,544.00 | K30: 18 | L30: 18-05-2026 | M30: 4,35,975 | N30: 3.163 | O30: 13,78,988.93 | P30: 1378.99 | R30: 13,77,609.94 | S30: 13,77,730.00 | T30: 120.06392 | U30: 19.05.2026
A31: 19 | B31: 19-05-2026 | C31: 3,74,000 | D31: 2.719 | E31: 10,16,906.00 | F31: 1017 | G31: 10,15,889.00 | K31: 19 | L31: 19-05-2026 | M31: 3,74,000 | N31: 2.749 | O31: 10,28,126.00 | P31: 1028.13 | R31: 10,27,097.87 | S31: 10,27,113.00 | T31: 15.126 | U31: 20-05-2027
A32: 20 | B32: 20-05-2026 | C32: 4,31,000 | D32: 2.693 | E32: 11,60,683.00 | F32: 1161 | G32: 11,59,522.00 | K32: 20 | L32: 20-05-2026 | M32: 4,31,000 | N32: 2.723 | O32: 11,73,613.00 | P32: 1173.61 | R32: 11,72,439.39 | S32: 11,72,299.00 | T32: -140.387 | U32: 21-05-2026
A33: 21 | B33: 21-05-2026 | C33: 7,32,075 | D33: 2.735 | E33: 20,02,225.00 | F33: 2002 | G33: 20,00,223.00 | K33: 21 | L33: 21-05-2026 | M33: 7,32,075 | N33: 2.765 | O33: 20,24,187.38 | P33: 2024.19 | R33: 20,22,163.19 | S33: 20,21,937.00 | T33: -226.18762 | U33: 22-05-2026
A34: 22 | B34: 22-05-2026 | C34: 7,87,600 | D34: 2.735 | E34: 21,54,086.00 | F34: 2154 | G34: 21,51,932.00 | K34: 22 | L34: 22-05-2026 | M34: 7,87,600 | N34: 2.765 | O34: 21,77,714.00 | P34: 2177.71 | R34: 21,75,536.29 | S34: 21,75,485.00 | T34: -51.286 | U34: 25-05-2026
A35: 23 | B35: 23-05-2026 | C35: 8,58,250 | D35: 3.111 | E35: 26,70,016.00 | F35: 2670 | G35: 26,67,346.00 | K35: 23 | L35: 23-05-2026 | M35: 8,58,250 | N35: 3.141 | O35: 26,95,763.25 | P35: 2695.76 | R35: 26,93,067.49 | S35: 26,93,128.00 | T35: 60.51325 | U35: 25-05-2026
A36: 24 | B36: 24-05-2026 | C36: 9,02,300 | D36: 2.644 | E36: 23,85,681.00 | F36: 2386 | G36: 23,83,295.00 | K36: 24 | L36: 24-05-2026 | M36: 9,02,300 | N36: 2.674 | O36: 24,12,750.20 | P36: 2412.75 | R36: 24,10,337.45 | S36: 24,10,371.00 | T36: 33.5502 | U36: 25-05-2026
... A43: 31 | B43: 31-05-2026 | C43: 7,90,400 | D43: 1.539 | E43: 12,16,426.00 | F43: 1216 | G43: 12,15,210.00 | K43: 31 | L43: 31-05-2026 | M43: 7,90,400 | N43: 1.569 | O43: 12,40,137.60 | P43: 1240.14 | R43: 12,38,897.46 | S43: 12,39,174.00 | T43: 276.5376 | U43: 01.05.2026
B44: Total | C44: 1,70,57,018.00 | E44: s | F44: 39649 | G44: ############ | H44: - | I44: - | J44: - | M44: 1,70,57,018.00 | O44: 4,01,59,255.67 | P44: 40159.26 | R44: 4,01,19,096.42 | S44: 4,01,19,731.00 | T44: 634.58
A45: 46168
A46: 1 | B46: 46028 | C46: 8,20,525 | D46: 1.974 | E46: 16,19,716.00 | F46: 1620 | G46: 16,18,096.00 | K46: 1 | L46: 46028 | M46: 8,20,525 | N46: 2.004 | O46: 16,44,332.10 | P46: 1644.33 | Q46: 1644 | R46: 16,42,687.77 | S46: 16,42,347.00 | T46: -340.7679 | U46: 46059
A47: 2 | B47: 46059 | C47: 8,55,275 | D47: 2.715 | E47: 23,22,072.00 | F47: 2322 | G47: 23,19,750.00 | K47: 2 | L47: 46059 | M47: 8,55,275 | N47: 2.745 | O47: 23,47,729.88 | P47: 2347.73 | Q47: 2348 | R47: 23,45,382.15 | S47: 23,45,328.00 | T47: -54.145125 | U47: 46087
A48: 3 | B48: 46087 | C48: 6,76,150 | D48: 3.006 | E48: 20,32,507.00 | F48: 2033 | G48: 20,30,474.00 | K48: 3 | L48: 46087 | M48: 6,76,150 | N48: 3.036 | O48: 20,52,791.40 | P48: 2052.79 | Q48: 2053 | R48: 20,50,738.61 | S48: 20,50,888.00 | T48: 149.3914 | U48: 46118
A49: 4 | B49: 46118 | C49: 8,57,600 | D49: 2.852 | E49: 24,45,875.00 | F49: 2446 | G49: 24,43,429.00 | K49: 4 | L49: 46118 | M49: 8,57,600 | N49: 2.882 | O49: 24,71,603.20 | P49: 2471.6 | Q49: 2472 | R49: 24,69,131.60 | S49: 24,69,181.00 | T49: 49.4032 | U49: 46148
A50: 5 | B50: 46148 | C50: 7,91,600 | D50: 2.689 | E50: 21,28,612.00 | F50: 2129 | G50: 21,26,483.00 | K50: 5 | L50: 46148 | M50: 7,91,600 | N50: 2.719 | O50: 21,52,360.40 | P50: 2152.36 | Q50: 2152 | R50: 21,50,208.04 | S50: 21,49,983.00 | T50: -225.0396 | U50: 46179
A51: 6 | B51: 46179 | C51: 8,45,018 | D51: 2.444 | E51: 20,65,224.00 | F51: 2065 | G51: 20,63,159.00 | K51: 6 | L51: 46179 | M51: 8,45,018 | N51: 2.474 | O51: 20,90,574.53 | P51: 2090.57 | Q51: 2090 | R51: 20,88,483.96 | S51: 20,88,369.00 | T51: -114.95747 | U51: 46240
A52: 7 | B52: 46209 | C52: 8,68,975 | D52: 2.215 | E52: 19,24,780.00 | F52: 1925 | G52: 19,22,855.00 | K52: 7 | L52: 46209 | M52: 8,68,975 | N52: 2.245 | O52: 19,50,848.88 | P52: 1950.85 | Q52: 1950 | R52: 19,48,898.03 | S52: 19,48,498.00 | T52: -400.03 | U52: 46240
A53: 8 | B53: 46240 | C53: 8,13,400 | D53: 2.402 | E53: 19,53,787.00 | F53: 1954 | G53: 19,51,833.00 | K53: 8 | L53: 46240 | M53: 8,13,400 | N53: 2.432 | O53: 19,78,188.80 | P53: 1978.19 | Q53: 1978 | R53: 19,76,210.61 | S53: 19,76,369.00 | T53: 158.39 | U53: 46271
A54: 9 | B54: 46271 | C54: 9,23,100 | D54: 2.354 | E54: 21,72,977.00 | F54: 2173 | G54: 21,70,804.00 | K54: 9 | L54: 46271 | M54: 9,23,100 | N54: 2.384 | O54: 22,00,670.40 | P54: 2200.67 | Q54: 2201 | R54: 21,98,469.73 | S54: 21,98,519.00 | T54: 49.27 | U54: 46301
A55: 10 | B55: 46301 | C55: 6,76,900 | D55: 2.58 | E55: 17,46,402.00 | F55: 1746 | G55: 17,44,656.00 | K55: 10 | L55: 46301 | M55: 6,76,900 | N55: 2.61 | O55: 17,66,709.00 | P55: 1766.71 | Q55: 1767 | R55: 17,64,942.29 | S55: 17,64,971.00 | T55: 28.709 | U55: 46332
B56: 46332 | C56: 7,25,600 | D56: 2.559 | E56: 18,56,810.00 | F56: 1857 | G56: 18,54,953.00 | K56: 11 | L56: 46332 | M56: 7,25,600 | N56: 2.589 | O56: 18,78,578.40 | P56: 1878.58 | Q56: 1879 | R56: 18,76,699.82 | S56: 18,76,872.00 | T56: 172.178 | U56: 46362
B57: 46362 | C57: 9,07,425 | D57: 2.282 | E57: 20,70,744.00 | F57: 2071 | G57: 20,68,673.00 | K57: 12 | L57: 46362 | M57: 9,07,425 | N57: 2.312 | O57: 20,97,966.60 | P57: 2097.97 | Q57: 2098 | R57: 20,95,868.63 | S57: 20,95,909.00 | T57: 40.367 | U57: 15/06/2026
B58: 13-06-2026 | C58: 10,31,750 | D58: 1.795 | E58: 18,51,991.00 | F58: 1852 | G58: 18,50,139.00 | K58: 13 | L58: 13-06-2026 | M58: 10,31,750 | N58: 1.825 | O58: 18,82,943.75 | P58: 1882.94 | Q58: 1883 | R58: 18,81,060.81 | S58: 18,80,945.00 | T58: -115.806 | U58: 15/06/2026
B59: 14-06-2026 | C59: 11,05,475 | D59: 1.553 | E59: 17,16,803.00 | F59: 1717 | G59: 17,15,086.00 | K59: 14 | L59: 14-06-2026 | M59: 11,05,475 | N59: 1.583 | O59: 17,49,966.93 | P59: 1749.97 | Q59: 1750 | R59: 17,48,216.96 | S59: 17,48,008.00 | T59: -208.958 | U59: 15/06/2026
B60: 15-06-2026 | C60: 10,35,100 | D60: 2.085 | E60: 21,58,184.00 | F60: 2158 | G60: 21,56,026.00 | K60: 15 | L60: 15-06-2026 | M60: 10,35,100 | N60: 2.115 | O60: 21,89,236.50 | P60: 2189.24 | Q60: 2189 | R60: 21,87,047.26 | S60: 21,87,150.00 | T60: 102.737 | U60: 16-06-2026
B61: 16-06-2026 | C61: 11,26,775 | D61: 2.361 | E61: 26,60,316.00 | F61: 2660 | G61: 26,57,656.00 | K61: 16 | L61: 16-06-2026 | M61: 11,26,775 | N61: 2.391 | O61: 26,94,119.03 | P61: 2694.12 | Q61: 2694 | R61: 26,91,424.91 | S61: 26,90,914.00 | T61: -510.906 | U61: 17-06-2026
B62: 17-06-2026 | C62: 10,20,825 | D62: 2.327 | E62: 23,75,460.00 | F62: 2375 | G62: 23,73,085.00 | K62: 17 | L62: 17-06-2026 | M62: 10,20,825 | N62: 2.357 | O62: 24,06,084.53 | P62: 2406.08 | Q62: 2406 | R62: 24,03,678.44 | S62: 24,03,991.00 | T62: 312.56 | U62: 18-06-2026
B63: 18-06-2026 | C63: 7,26,125 | D63: 2.789 | E63: 20,25,163.00 | F63: 2025 | G63: 20,23,138.00 | K63: 18 | L63: 18-06-2026 | M63: 7,26,125 | N63: 2.819 | O63: 20,46,946.38 | P63: 2046.95 | Q63: 2047 | R63: 20,44,899.43 | S63: 20,44,623.00 | T63: -276.429 | U63: 19-05-2026
B64: 19-06-2026 | C64: 10,10,050 | D64: 2.784 | E64: 28,11,979.00 | F64: 2812 | G64: 28,09,167.00 | K64: 19 | L64: 19-06-2026 | M64: 10,10,050 | N64: 2.814 | O64: 28,42,280.70 | P64: 2842.28 | Q64: 2842 | R64: 28,39,438.42 | S64: 28,39,298.00 | T64: -140.419 | U64: 20-05-2026
B65: 20-06-2026 | C65: 10,85,850 | D65: 2.675 | E65: 29,04,649.00 | F65: 2905 | G65: 29,01,744.00 | K65: 20 | L65: 20-06-2026 | M65: 10,85,850 | N65: 2.705 | O65: 29,37,224.25 | P65: 2937.22 | Q65: 2945 | R65: 29,34,287.03 | S65: 29,41,924.00 | T65: 7636.974 | U65: 22-06-2026
B66: 21-06-2026 | C66: 13,11,000 | D66: 2.659 | E66: 34,85,949.00 | F66: 3486 | G66: 34,82,463.00 | K66: 21 | L66: 21-06-2026 | M66: 13,11,000 | N66: 2.689 | O66: 35,25,279.00 | P66: 3525.28 | Q66: 3525 | R66: 35,21,753.72 | S66: 35,21,301.00 | T66: -452.721 | U66: 22-06-2026
B67: 22-06-2026 | C67: 11,29,375 | D67: 2.682 | E67: 30,28,984.00 | F67: 3029 | G67: 30,25,955.00 | K67: 22 | L67: 22-06-2026 | M67: 11,29,375 | N67: 2.712 | O67: 30,62,865.00 | P67: 3062.87 | Q67: 3063 | R67: 30,59,802.14 | S67: 30,60,065.00 | T67: 262.865 | U67: 23-06-2026
B68: 23-06-2026 | C68: 4,54,075 | D68: 3.373 | E68: 15,31,595.00 | F68: 1532 | G68: 15,30,063.00 | K68: 23 | L68: 23-06-2026 | M68: 4,54,075 | N68: 3.403 | O68: 15,45,217.23 | P68: 1545.22 | Q68: 1545 | R68: 15,43,672.01 | S68: 15,43,718.00 | T68: 45.992 | U68: 24-06-2026
B69: 24-06-2026 | C69: 11,43,550 | D69: 2.258 | E69: 25,82,136.00 | F69: 2582 | G69: 25,79,554.00 | K69: 24 | L69: 24-06-2026 | M69: 11,43,550 | N69: 2.288 | O69: 26,16,442.40 | P69: 2616.44 | Q69: 2617 | R69: 26,13,825.96 | S69: 26,14,311.00 | T69: 485.0424 | U69: 25-06-2026
... B74: 29-06-2026 | C74: 12,12,150 | D74: 2.484 | E74: 30,10,981.00 | F74: 3011 | G74: 30,07,970.00 | K74: 29 | L74: 29-06-2026 | M74: 12,12,150 | N74: 2.514 | O74: 30,47,345.10 | P74: 3047.35 | Q74: 3047 | R74: 30,44,297.75 | S74: 30,44,286.00 | T74: -11.7549 | U74: 30-06-2026
B75: 30-06-2026 | C75: 11,40,050 | D75: 2.85 | E75: 32,49,143.00 | F75: 3249 | G75: 32,45,894.00 | K75: 30 | L75: 30-06-2026 | M75: 11,40,050 | N75: 2.88 | O75: 32,83,344.00 | P75: 3283.34 | Q75: 3284 | R75: 32,80,060.66 | S75: 32,80,527.00 | T75: 466.344 | U75: 46029
B76: Total | C76: 2,93,03,968.00 | F76: 71406 | G76: 7,13,33,248.00 | H76: - | I76: - | J76: - | M76: 2,93,03,968.00 | O76: 7,22,83,771.71 | P76: 72283.77 | Q76: 72292 | R76: 7,22,11,487.94 | S76: 7,22,19,123.00 | T76: 7635.06
B77: 46029 | C77: 1966050 | D77: 2.109 | E77: 4146400 | F77: =E77*0.1% -> 4146.4 | G77: =E77 + F77 -> 4150546.4 | K77: 31 | L77: 46029 | M77: =C77 -> 1966050 | N77: =D77 + 0.03 -> 2.139 | O77: =M77 * N77 -> 4205381 | P77: =O77*0.1% -> 4205.3809 | Q77: 4205 | R77: =O77 - P77 -> 4201175.6 | S77: 4200575 | T77: =R77 - S77 -> 600.56905 | U77: 46060
B78: 46060 | C78: 2104425 | D78: 1.906 | E78: 4011034 | F78: =E78*0.1% -> 4011.034 | G78: =E78 + F78 -> 4015045 | K78: 32 | L78: 46060 | M78: =C78 -> 2104425 | N78: =D78 + 0.03 -> 1.936 | O78: =M78 * N78 -> 4074166.8 | P78: =O78*0.1% -> 4074.1668 | Q78: 4074 | R78: =O78 - P78 -> 4070092.6 | S78: 4070034 | T78: =R78 - S78 -> 58.6332 | U78: 46088
B79: 46088 | C79: 2115000 | D79: 2.032 | E79: 4297680 | F79: =E79*0.1% -> 4297.68 | G79: =E79 + F79 -> 4301977.7 | K79: 33 | L79: 46088 | M79: =C79 -> 2115000 | N79: =D79 + 0.03 -> 2.062 | O79: =M79 * N79 -> 4361130 | P79: =O79*0.1% -> 4361.13 | Q79: 4360 | R79: =O79 - P79 -> 4356768.9 | S79: 4355854 | T79: =R79 - S79 -> 914.87 | U79: 46119
B80: 46119 | C80: 2121075 | D80: 1.815 | E80: 3849751 | F80: =E80*0.1% -> 3849.751 | G80: =E80 + F80 -> 3853600.8 | K80: 34 | L80: 46119 | M80: =C80 -> 2121075 | N80: =D80 + 0.03 -> 1.845 | O80: =M80 * N80 -> 3913383.4 | P80: =O80*0.1% -> 3913.3834 | Q80: 3913 | R80: =O80 - P80 -> 3909470 | S80: 3909015 | T80: =R80 - S80 -> 454.99162 | U80: 46180
B81: 46149 | C81: 2156675 | D81: 1.37 | E81: 2954645 | F81: =E81*0.1% -> 2954.645 | G81: =E81 + F81 -> 2957599.6 | K81: 35 | L81: 46149 | M81: =C81 -> 2156675 | N81: =D81 + 0.03 -> 1.4 | O81: =M81 * N81 -> 3019345 | P81: =O81*0.1% -> 3019.345 | Q81: 3020 | R81: =O81 - P81 -> 3016325.7 | S81: 3016859 | T81: =R81 - S81 -> -533.345 | U81: 46180
B82: 46180 | C82: 1976375 | D82: 1.495 | E82: 2954681 | F82: =E82*0.1% -> 2954.681 | G82: =E82 + F82 -> 2957635.7 | K82: 36 | L82: 46180 | M82: =C82 -> 1976375 | N82: =D82 + 0.03 -> 1.525 | O82: =M82 * N82 -> 3013971.9 | P82: =O82*0.1% -> 3013.9719 | Q82: 3013 | R82: =O82 - P82 -> 3010957.9 | S82: 3010035 | T82: =R82 - S82 -> 922.90313 | U82: 46210
B83: 46210 | C83: 1988525 | D83: 1.82 | E83: 3619116 | F83: =E83*0.1% -> 3619.116 | G83: =E83 + F83 -> 3622735.1 | K83: 37 | L83: 46210 | M83: =C83 -> 1988525 | N83: =D83 + 0.03 -> 1.85 | O83: =M83 * N83 -> 3678771.2 | P83: =O83*0.1% -> 3678.7712 | Q83: 3678 | R83: =O83 - P83 -> 3675092.5 | S83: 3674441 | T83: =R83 - S83 -> 651.47875 | U83: 46241
B84: 46241 | C84: 2059550 | D84: 1.691 | E84: 3482699 | F84: =E84*0.1% -> 3482.699 | G84: =E84 + F84 -> 3486181.7 | K84: 38 | L84: 46241 | M84: =C84 -> 2059550 | N84: =D84 + 0.03 -> 1.721 | O84: =M84 * N84 -> 3544485.5 | P84: =O84*0.1% -> 3544.4855 | Q84: 3545 | R84: =O84 - P84 -> 3540941.1 | S84: 3541125 | T84: =R84 - S84 -> -183.93555 | U84: 46272

Sheet TDS
A1: Application date | B1: Appication No | C1: Vender name | E1: PAN | F1: Amount (Rs.) | G1: TDS amount Deducted by SJVN | H1: Total TDS amount | I1: Challan No | J1: Challan Date
A2: 45015 | C2: Delhi Transco Limited | D2: Delhi STU | E2: AABCD6342A | F2: 114762 | G2: =F2*0.1 -> 11476.2 | K2: =F2-G2 -> 103285.8
A3: 45015 | D3: West Bengal STU | E3: AAACW6952G | F3: 71520 | G3: =F3*0.1 -> 7152 | K3: =F3-G3 -> 64368
A4: 45027 | D4: Delhi STU | E4: AABCD6342A | F4: 54703 | G4: =F4*0.1 -> 5470.3 | H4: =G4+G5 -> 8879.4
A5: 45027 | D5: West Bengal STU | E5: AAACW6952G | F5: 34091 | G5: =F5*0.1 -> 3409.1
A6: 45028 | D6: Delhi STU | E6: AABCD6342A | F6: 57381 | G6: =F6*0.1 -> 5738.1 | H6: =G6+G7 -> 9314.1
A7: 45028 | D7: West Bengal STU | E7: AAACW6952G | F7: 35760 | G7: =F7*0.1 -> 3576
A10: 45029 | D10: Delhi STU | E10: AABCD6342A | F10: 57381 | G10: =F10*0.1 -> 5738.1 | H10: =G10+G11 -> 9314.1
A11: 45029 | D11: West Bengal STU | E11: AAACW6952G | F11: 35760 | G11: =F11*0.1 -> 3576
A13: 45030 | D13: Delhi STU | E13: AABCD6342A | F13: 57381 | G13: =F13*0.1 -> 5738.1 | H13: =G13+G14 -> 9314.1
A14: 45030 | D14: West Bengal STU | E14: AAACW6952G | F14: 35760 | G14: =F14*0.1 -> 3576
A16: 45031 | D16: Delhi STU | E16: AABCD6342A | F16: 57381 | G16: =F16*0.1 -> 5738.1 | H16: =G16+G17 -> 9314.1
A17: 45031 | D17: West Bengal STU | E17: AAACW6952G | F17: 35760 | G17: =F17*0.1 -> 3576
A19: 45032 | D19: Delhi STU | E19: AABCD6342A | F19: 57381 | G19: =F19*0.1 -> 5738.1 | H19: =G19+G20 -> 9314.1
A20: 45032 | D20: West Bengal STU | E20: AAACW6952G | F20: 35760 | G20: =F20*0.1 -> 3576
A23: 45033 | D23: Delhi STU | E23: AABCD6342A | F23: 57381 | G23: =F23*0.1 -> 5738.1 | H23: =G23+G24 -> 9314.1
A24: 45033 | D24: West Bengal STU | E24: AAACW6952G | F24: 35760 | G24: =F24*0.1 -> 3576
A27: 45034 | D27: Delhi STU | E27: AABCD6342A | F27: 57381 | G27: =F27*0.1 -> 5738.1 | H27: =G27+G28 -> 9314.1
A28: 45034 | D28: West Bengal STU | E28: AAACW6952G | F28: 35760 | G28: =F28*0.1 -> 3576
A31: 45035 | D31: Delhi STU | E31: AABCD6342A | F31: 57381 | G31: =F31*0.1 -> 5738.1 | H31: =G31+G32 -> 9314.1
A32: 45035 | D32: West Bengal STU | E32: AAACW6952G | F32: 35760 | G32: =F32*0.1 -> 3576
A35: 45036 | D35: Delhi STU | E35: AABCD6342A | F35: 76508 | G35: 7650.8 | H35: =G35+G36 -> 12418.8
A36: 45036 | D36: West Bengal STU | E36: AAACW6952G | F36: 47680 | G36: 4768

Sheet schedule
A1: Applicant | C1: SJVNL
A2: From State | C2: WEST BENGAL
A3: From Utility | C3: IPCL_WB
A4: To State | C4: DELHI
A5: To Utility | C5: NDMC
A6: IR Link | C6: East-North
A7: Appr. No | C7: NR/2023/11151/D
A8: Time Block | B8: Time Desc
A9: 1 | B9: 00:00-00:15 | C9: 0
A10: 2 | B10: 00:15-00:30 | C10: 0
A11: 3 | B11: 00:30-00:45 | C11: 0
A12: 4 | B12: 00:45-01:00 | C12: 0
A13: 5 | B13: 01:00-01:15 | C13: 0
A14: 6 | B14: 01:15-01:30 | C14: 0
A15: 7 | B15: 01:30-01:45 | C15: 0
A16: 8 | B16: 01:45-02:00 | C16: 0
A17: 9 | B17: 02:00-02:15 | C17: 0
A18: 10 | B18: 02:15-02:30 | C18: 0
A19: 11 | B19: 02:30-02:45 | C19: 0
A20: 12 | B20: 02:45-03:00 | C20: 0
... A104: 96 | B104: 23:45-24:00 | C104: 0
B105: MWHR | C105: =SUM(C9:C104)*15/60 -> 300
B106: Maximum | C106: =MAX(C9:C104) -> 40
B107: Minimum | C107: =MIN(C9:C104) -> 0
B108: Average | C108: =AVERAGE(C9:C104) -> 12.5

Sheet OA Bills
A2: Schedule of Payment
A4: From Date | B4: To Date | C4: SJVN App. No on NOAR | D4: NOAR Acceptance No | E4: Total Quantum (MWh) | F4: ISTS Charges | H4: STU Charges | J4: Operating Charges | O4: Total OA Charges
E5: MWH | F5: Injection | G5: Drawal | H5: West Bengal STU | I5: Delhi STU | J5: ERLDC | K5: NRLDC | L5: West Bengal -SLDC | M5: Delhi SLDC | N5: Application Fee on NOAR Portal | O5: Total OA Charges | P5: OA Charges to be born by Seller | Q5: OA Charges to be born by Buyer
F6: 0 | G6: 0 | H6: 238.4 | I6: 382.54 | J6: 1000 | K6: 1000 | L6: 1000 | M6: 1000 | N6: 5000
F7: Rs./Mwh | G7: Rs./Mwh | H7: Rs./Mwh | I7: Rs./Mwh | J7: Rs./ Day | K7: Rs./ Day | L7: Rs./ Day | M7: Rs./ Day
A8: 45016 | B8: 45016 | C8: SJVN/30032023 | D8: NR/2023/11151/D | E8: 300 | F8: =F$6*$E8 -> 0 | G8: =G$6*$E8 -> 0 | H8: =H$6*$E8 -> 71520 | I8: =I$6*$E8 -> 114762 | J8: =$J$6 -> 1000 | K8: =$K$6 -> 1000 | L8: =$L$6 -> 1000 | M8: =$M$6 -> 1000 | N8: =$N$6 -> 5000 | O8: =SUM(F8:N8) -> 195282 | P8: =N8+M8+K8+I8+G8 -> 121762 | Q8: =L8+J8+H8+F8 -> 73520
A9: 45234 | B9: 45234 | C9: =#REF! -> #REF! | D9: =#REF! -> #REF! | E9: =#REF! -> #REF! | F9: =F$6*$E9 -> #REF! | G9: =G$6*$E9 -> #REF! | H9: =H$6*$E9 -> #REF! | I9: =I$6*$E9 -> #REF! | J9: =$J$6 -> 1000 | K9: =$K$6 -> 1000 | L9: =$L$6 -> 1000 | M9: =$M$6 -> 1000 | N9: =$N$6 -> 5000 | O9: =SUM(F9:N9) -> #REF! | P9: =N9+M9+K9+I9+G9 -> #REF! | Q9: =L9+J9+H9+F9 -> #REF!
A10: =#REF! -> #REF! | B10: =#REF! -> #REF! | C10: =#REF! -> #REF! | D10: =#REF! -> #REF! | E10: =#REF! -> #REF! | F10: =F$6*$E10 -> #REF! | G10: =G$6*$E10 -> #REF! | H10: =H$6*$E10 -> #REF! | I10: =I$6*$E10 -> #REF! | J10: =J6 -> 1000 | K10: =K6 -> 1000 | L10: =L6 -> 1000 | M10: =M6 -> 1000 | N10: =N6 -> 5000 | O10: =SUM(F10:N10) -> #REF! | P10: =N10+M10+K10+I10+G10 -> #REF! | Q10: =L10+J10+H10+F10 -> #REF!

Sheet TDS to be paid
A1: Application Id | B1: Application No | C1: Approval No | D1: Name | E1: PAN | F1: TDS Deducted by SJVN | G1: Total Amount
A2: 38199 | B2: SJVN/2023-24/02/11042023 | C2: NR/2023/11468/D | D2: GRID-INDIA | E2: AAFCP2086B | F2: 0
A3: 38199 | B3: SJVN/2023-24/02/11042023 | C3: NR/2023/11468/D | D3: Delhi SLDC | E3: AABCD6342A | F3: 0
A4: 38199 | B4: SJVN/2023-24/02/11042023 | C4: NR/2023/11468/D | D4: West Bengal SLDC | E4: AAACW6952G | F4: 0
A5: 38199 | B5: SJVN/2023-24/02/11042023 | C5: NR/2023/11468/D | D5: Delhi STU | E5: AABCD6342A | F5: 5738 | G5: 57381
A6: 38199 | B6: SJVN/2023-24/02/11042023 | C6: NR/2023/11468/D | D6: West Bengal STU | E6: AAACW6952G | F6: 3576 | G6: 35760
A7: 38308 | B7: SJVN/2023-24/03/12042023 | C7: NR/2023/11494/C | D7: GRID-INDIA | E7: AAFCP2086B | F7: 0
A8: 38308 | B8: SJVN/2023-24/03/12042023 | C8: NR/2023/11494/C | D8: Delhi SLDC | E8: AABCD6342A | F8: 0
A9: 38308 | B9: SJVN/2023-24/03/12042023 | C9: NR/2023/11494/C | D9: West Bengal SLDC | E9: AAACW6952G | F9: 0
A10: 38308 | B10: SJVN/2023-24/03/12042023 | C10: NR/2023/11494/C | D10: Delhi STU | E10: AABCD6342A | F10: 5738 | G10: 57381
A11: 38308 | B11: SJVN/2023-24/03/12042023 | C11: NR/2023/11494/C | D11: West Bengal STU | E11: AAACW6952G | F11: 3576 | G11: 35760
A12: 38429 | B12: SJVN/2023-24/04/13042023 | C12: NR/2023/11522/C | D12: GRID-INDIA | E12: AAFCP2086B | F12: 0
A13: 38429 | B13: SJVN/2023-24/04/13042023 | C13: NR/2023/11522/C | D13: Delhi SLDC | E13: AABCD6342A | F13: 0
A14: 38429 | B14: SJVN/2023-24/04/13042023 | C14: NR/2023/11522/C | D14: West Bengal SLDC | E14: AAACW6952G | F14: 0
A15: 38429 | B15: SJVN/2023-24/04/13042023 | C15: NR/2023/11522/C | D15: Delhi STU | E15: AABCD6342A | F15: 5738 | G15: 57381
A16: 38429 | B16: SJVN/2023-24/04/13042023 | C16: NR/2023/11522/C | D16: West Bengal STU | E16: AAACW6952G | F16: 3576 | G16: 35760
A17: 38567 | B17: SJVN/2023-24/05/14042023 | C17: NR/2023/11547/C | D17: GRID-INDIA | E17: AAFCP2086B | F17: 0
A18: 38567 | B18: SJVN/2023-24/05/14042023 | C18: NR/2023/11547/C | D18: Delhi SLDC | E18: AABCD6342A | F18: 0
A19: 38567 | B19: SJVN/2023-24/05/14042023 | C19: NR/2023/11547/C | D19: West Bengal SLDC | E19: AAACW6952G | F19: 0
A20: 38567 | B20: SJVN/2023-24/05/14042023 | C20: NR/2023/11547/C | D20: Delhi STU | E20: AABCD6342A | F20: 5738 | G20: 57381
A21: 38567 | B21: SJVN/2023-24/05/14042023 | C21: NR/2023/11547/C | D21: West Bengal STU | E21: AAACW6952G | F21: 3576 | G21: 35760
A22: 39168 | B22: SJVN/2023-24/09/18042023 | C22: NR/2023/11678/C | D22: GRID-INDIA | E22: AAFCP2086B | F22: 200 | G22: 2000
A23: 39168 | B23: SJVN/2023-24/09/18042023 | C23: NR/2023/11678/C | D23: Delhi SLDC | E23: AABCD6342A | F23: 100 | G23: 1000
A24: 39168 | B24: SJVN/2023-24/09/18042023 | C24: NR/2023/11678/C | D24: West Bengal SLDC | E24: AAACW6952G | F24: 100 | G24: 1000
A25: 39168 | B25: SJVN/2023-24/09/18042023 | C25: NR/2023/11678/C | D25: Delhi STU | E25: AABCD6342A | F25: 5738 | G25: 57381
A26: 39168 | B26: SJVN/2023-24/09/18042023 | C26: NR/2023/11678/C | D26: West Bengal STU | E26: AAACW6952G | F26: 3576 | G26: 35760
A27: 39357 | B27: SJVN/2023-24/10/19042023 | C27: NR/2023/11720/C | D27: GRID-INDIA | E27: AAFCP2086B | F27: 700 | G27: 7000
A28: 39357 | B28: SJVN/2023-24/10/19042023 | C28: NR/2023/11720/C | D28: Delhi SLDC | E28: AABCD6342A | F28: 100 | G28: 1000
A29: 39357 | B29: SJVN/2023-24/10/19042023 | C29: NR/2023/11720/C | D29: West Bengal SLDC | E29: AAACW6952G | F29: 100 | G29: 1000
A30: 39357 | B30: SJVN/2023-24/10/19042023 | C30: NR/2023/11720/C | D30: Delhi STU | E30: AABCD6342A | F30: 7651 | G30: 76508
A31: 39357 | B31: SJVN/2023-24/10/19042023 | C31: NR/2023/11720/C | D31: West Bengal STU | E31: AAACW6952G | F31: 4768 | G31: 47680
A32: 38091 | B32: SJVN/2023-24/10042023 | C32: NR/2023/11443/C | D32: GRID-INDIA | E32: AAFCP2086B | F32: 0
A33: 38091 | B33: SJVN/2023-24/10042023 | C33: NR/2023/11443/C | D33: Delhi SLDC | E33: AABCD6342A | F33: 0
A34: 38091 | B34: SJVN/2023-24/10042023 | C34: NR/2023/11443/C | D34: West Bengal SLDC | E34: AAACW6952G | F34: 0
A35: 38091 | B35: SJVN/2023-24/10042023 | C35: NR/2023/11443/C | D35: Delhi STU | E35: AABCD6342A | F35: 5470 | G35: 54703
A36: 38091 | B36: SJVN/2023-24/10042023 | C36: NR/2023/11443/C | D36: West Bengal STU | E36: AAACW6952G | F36: 3409 | G36: 34091
A37: 39648 | B37: SJVN/2023-24/12/19042023 | C37: NR/2023/11771/D | D37: GRID-INDIA | E37: AAFCP2086B | F37: 700 | G37: 7000
A38: 39648 | B38: SJVN/2023-24/12/19042023 | C38: NR/2023/11771/D | D38: Delhi SLDC | E38: AABCD6342A | F38: 100 | G38: 1000
A39: 39648 | B39: SJVN/2023-24/12/19042023 | C39: NR/2023/11771/D | D39: West Bengal SLDC | E39: AAACW6952G | F39: 100 | G39: 1000
A40: 39648 | B40: SJVN/2023-24/12/19042023 | C40: NR/2023/11771/D | D40: Delhi STU | E40: AABCD6342A | F40: 7651 | G40: 76508
A41: 39648 | B41: SJVN/2023-24/12/19042023 | C41: NR/2023/11771/D | D41: West Bengal STU | E41: AAACW6952G | F41: 4768 | G41: 47680
A42: 39835 | B42: SJVN/2023-24/13/19042023 | C42: NR/2023/11799/D | D42: GRID-INDIA | E42: AAFCP2086B | F42: 700 | G42: 7000
A43: 39835 | B43: SJVN/2023-24/13/19042023 | C43: NR/2023/11799/D | D43: Delhi SLDC | E43: AABCD6342A | F43: 100 | G43: 1000
A44: 39835 | B44: SJVN/2023-24/13/19042023 | C44: NR/2023/11799/D | D44: West Bengal SLDC | E44: AAACW6952G | F44: 100 | G44: 1000
A45: 39835 | B45: SJVN/2023-24/13/19042023 | C45: NR/2023/11799/D | D45: Delhi STU | E45: AABCD6342A | F45: 7651 | G45: 76508
A46: 39835 | B46: SJVN/2023-24/13/19042023 | C46: NR/2023/11799/D | D46: West Bengal STU | E46: AAACW6952G | F46: 4768 | G46: 47680
... A61: 40557 | B61: SJVN/2023-24/16/29042023 | C61: NR/2023/12019/C | D61: West Bengal STU | E61: AAACW6952G | F61: 1848 | G61: 18476
B62: 45047
A63: 43092 | B63: SJVN/2023-24/17/21052023 | C63: NR/2023/12722/D | D63: GRID-INDIA | E63: AAFCP2086B | F63: 700
A64: 43092 | B64: SJVN/2023-24/17/21052023 | C64: NR/2023/12722/D | D64: Delhi SLDC | E64: AABCD6342A | F64: 100
A65: 43092 | B65: SJVN/2023-24/17/21052023 | C65: NR/2023/12722/D | D65: West Bengal SLDC | E65: AAACW6952G | F65: 100
A66: 43092 | B66: SJVN/2023-24/17/21052023 | C66: NR/2023/12722/D | D66: Delhi STU | E66: AABCD6342A | F66: 6694
A67: 43092 | B67: SJVN/2023-24/17/21052023 | C67: NR/2023/12722/D | D67: West Bengal STU | E67: AAACW6952G | F67: 4172
A68: 43216 | B68: SJVN/2023-24/18/22052023 | C68: NR/2023/12743/D | D68: GRID-INDIA | E68: AAFCP2086B | F68: 700
A69: 43216 | B69: SJVN/2023-24/18/22052023 | C69: NR/2023/12743/D | D69: Delhi SLDC | E69: AABCD6342A | F69: 100
A70: 43216 | B70: SJVN/2023-24/18/22052023 | C70: NR/2023/12743/D | D70: West Bengal SLDC | E70: AAACW6952G | F70: 100
A71: 43216 | B71: SJVN/2023-24/18/22052023 | C71: NR/2023/12743/D | D71: Delhi STU | E71: AABCD6342A | F71: 7077
A72: 43216 | B72: SJVN/2023-24/18/22052023 | C72: NR/2023/12743/D | D72: West Bengal STU | E72: AAACW6952G | F72: 4410
A73: 43491 | B73: SJVN/2023-24/19/24052023 | C73: NR/2023/12815/C | D73: GRID-INDIA | E73: AAFCP2086B | F73: 700
A74: 43491 | B74: SJVN/2023-24/19/24052023 | C74: NR/2023/12815/C | D74: Delhi SLDC | E74: AABCD6342A | F74: 100
... A102: 43952 | B102: SJVN/2023-24/25/27052023 | C102: NR/2023/12972/C | D102: West Bengal STU | E102: AAACW6952G | F102: 4768
B103: 45078
A104: 45588 | B104: SJVN/2-23-24/32/08062023 | C104: NR/2023/13423/C | D104: GRID-INDIA | E104: AAFCP2086B | F104: 540
A105: 45588 | B105: SJVN/2-23-24/32/08062023 | C105: NR/2023/13423/C | D105: Delhi SLDC | E105: AABCD6342A | F105: 100
A106: 45588 | B106: SJVN/2-23-24/32/08062023 | C106: NR/2023/13423/C | D106: West Bengal SLDC | E106: AAACW6952G | F106: 100
A107: 45588 | B107: SJVN/2-23-24/32/08062023 | C107: NR/2023/13423/C | D107: Delhi STU | E107: AABCD6342A | F107: 7651
A108: 45588 | B108: SJVN/2-23-24/32/08062023 | C108: NR/2023/13423/C | D108: West Bengal STU | E108: AAACW6952G | F108: 4768
A109: 43789 | B109: SJVN/2023-24/23/26052023 | C109: NR/2023/12906/F | D109: GRID-INDIA | E109: AAFCP2086B | F109: 900
A110: 43789 | B110: SJVN/2023-24/23/26052023 | C110: NR/2023/12906/F | D110: Delhi SLDC | E110: AABCD6342A | F110: 200
A111: 43789 | B111: SJVN/2023-24/23/26052023 | C111: NR/2023/12906/F | D111: West Bengal SLDC | E111: AAACW6952G | F111: 200
A112: 43789 | B112: SJVN/2023-24/23/26052023 | C112: NR/2023/12906/F | D112: Delhi STU | E112: AABCD6342A | F112: 15302
A113: 43789 | B113: SJVN/2023-24/23/26052023 | C113: NR/2023/12906/F | D113: West Bengal STU | E113: AAACW6952G | F113: 9536
A114: 43789 | B114: SJVN/2023-24/23/26052023 | C114: NR/2023/12906/F | D114: INTEREST | F114: 51
A115: 44602 | B115: SJVN/2023-24/26/30052023 | C115: NR/2023/13145/F | D115: GRID-INDIA | E115: AAFCP2086B | F115: 1100
A116: 44602 | B116: SJVN/2023-24/26/30052023 | C116: NR/2023/13145/F | D116: Delhi SLDC | E116: AABCD6342A | F116: 300
A117: 44602 | B117: SJVN/2023-24/26/30052023 | C117: NR/2023/13145/F | D117: West Bengal SLDC | E117: AAACW6952G | F117: 300
A118: 44602 | B118: SJVN/2023-24/26/30052023 | C118: NR/2023/13145/F | D118: Delhi STU | E118: AABCD6342A | F118: 22952
A119: 44602 | B119: SJVN/2023-24/26/30052023 | C119: NR/2023/13145/F | D119: West Bengal STU | E119: AAACW6952G | F119: 14304
A120: 44606 | B120: SJVN/2023-24/27/02062023 | C120: NR/2023/13149/C | D120: GRID-INDIA | E120: AAFCP2086B | F120: 700
A121: 44606 | B121: SJVN/2023-24/27/02062023 | C121: NR/2023/13149/C | D121: Delhi SLDC | E121: AABCD6342A | F121: 100
A122: 44606 | B122: SJVN/2023-24/27/02062023 | C122: NR/2023/13149/C | D122: West Bengal SLDC | E122: AAACW6952G | F122: 100
A123: 44606 | B123: SJVN/2023-24/27/02062023 | C123: NR/2023/13149/C | D123: Delhi STU | E123: AABCD6342A | F123: 7651
A124: 44606 | B124: SJVN/2023-24/27/02062023 | C124: NR/2023/13149/C | D124: West Bengal STU | E124: AAACW6952G | F124: 4768
A125: 44869 | B125: SJVN/2023-24/29/04062023 | C125: NR/2023/13223/C | D125: GRID-INDIA | E125: AAFCP2086B | F125: 700
A126: 44869 | B126: SJVN/2023-24/29/04062023 | C126: NR/2023/13223/C | D126: Delhi SLDC | E126: AABCD6342A | F126: 100
... A149: 44741 | B149: SJVN/23-24/28/03062023 | C149: NR/2023/13192/C | D149: West Bengal STU | E149: AAACW6952G | F149: 4768
A150: 44741 | B150: SJVN/23-24/28/03062023 | C150: NR/2023/13192/C | D150: INTEREST | F150: 5

Sheet payment screenshot
A6: NDMC 1st Payment

Sheet pass
A1: url | B1: energx.iexindia.com
A2: iex participant ID | B2: N2DL0SJV000
A3: PASS | B3: Sjvniex@123
A6: url for pulse secure | B6: trading.iexindia.com

Sheet OA payments_NOAR
A1: ApplicationID | B1: ApplicationNo | C1: NetPayable | D1: PaidAmountFee | E1: PaidAmountFeeTds | F1: BilateralCharge | G1: BilateralTds | H1: Total | I1: TxAmountTotal | J1: Diff | K1: PaymentDueAmount | L1: PaymentStatus | M1: DueDate | N1: IsMigratedApp | O1: InterestCalculation | P1: Transactions
A2: 37017 | B2: SJVN/30032023 | C2: 195282 | D2: 5000 | E2: 0 | F2: 171654 | G2: 18628 | H2: 176654 | I2: 176654 | J2: 0 | K2: 0 | L2: Paid | M2: 45019.666 | N2: FALSE | O2: 0
A3: 38091 | B3: SJVN/2023-24/10042023 | C3: 97794 | D3: 5000 | E3: 0 | F3: 83915 | G3: 8879 | H3: 88915 | I3: 5000 | J3: -83915 | K3: 83915 | L3: Partially Paid | M3: 45029.692
A4: 38199 | B4: SJVN/2023-24/02/11042023 | C4: 102141 | D4: 5000 | E4: 0 | F4: 87827 | G4: 9314 | H4: 92827 | I4: 5000 | J4: -87827 | K4: 87827 | L4: Partially Paid | M4: 45030.536

Sheet Bill
D2: Energy Bill for 31 March 2023
A4: Sr. No | B4: Bill No | C4: Date | D4: Due Date | E4: Supplier | F4: Type of Energy | G4: Description | H4: Supply in kWh | I4: Rate (Rs.) | J4: Gross Amount (Rs.)
A5: 1 | B5: SJVN | C5: 45017 | D5: =C5+7 -> 45024 | E5: Kreate | F5: RE (Wind) | H5: 300000 | I5: 5.13 | J5: =I5*H5 -> 1539000
